Workbook
Name NumEval: 'Cálculo de % usabilidad'!$F$4
Name Relenacia: Valores!$J$5:$J$8
Name Relevancia: Valores!$J$5:$J$8
Name Tabla621: 'Tablas de relevancia'!$A$4:$Q$13
Name Tabla622: 'Tablas de relevancia'!$A$18:$Q$24
Name Tabla623: 'Tablas de relevancia'!$A$29:$Q$42
Name Tabla624: 'Tablas de relevancia'!$A$47:$Q$52
Name Tabla625: 'Tablas de relevancia'!$A$57:$Q$66
Name Tabla626: 'Tablas de relevancia'!$A$71:$Q$77
Name Tabla627: 'Tablas de relevancia'!$A$82:$Q$91
Name Tabla628: 'Tablas de relevancia'!$A$96:$Q$101
Name Tabla629: 'Tablas de relevancia'!$A$106:$Q$113
Name Tabla630: 'Tablas de relevancia'!$A$118:$Q$122
Name TipoDeSitio: 'Datos sitio'!$B$15
Name Tipos: Valores!$E$5:$E$20
Name Valores1: Valores!$A$5:$A$16
Name Valores2: Valores!$C$5:$C$10
Name ValoresRC: Valores!$J$5:$K$8
Name ValoresVC: Valores!$M$5:$N$21

Sheet Datos sitio
A1: Checklist para revisión heurística de usabilidad v.3beta | C1: 40756
A2: basada en la tesis de Mª del Carmen Suárez Torrente
A3: Sirius: Sistema de Evaluación de la Usabilidad Web Orientado al Usuario y basado en la Determinación de Tareas Críticas
A5: Autor: Olga Carreras Montoto | B5: (Usable y accesible)
A6: Mejoras de la v.3 por: Cecilio Sánchez «Cean» | B6: (leevel)
A7: Artículo: http://olgacarreras.blogspot.com/2011/07/sirius-nueva-sistema-para-la-evaluacion.html
A10: DATOS GENERALES DE LA EVALUACIÓN
A11: Evaluador | B11: GitHub Copilot
A12: Fecha de evaluación | B12: 46147
A13: Nombre del sitio evaluado | B13: Taxi Transfer Tenerife
A14: URL del sitio evaluado | B14: file:///index.html (prototipo local)
A15: Tipo de sitio evaluado | B15: Portal de Servicios | C15: (nota: no admite la definición de sitio híbrido, ver pp. 162 de la tesis)
A16: Navegador con el que se revisa | B16: Google Chrome
A17: Versión el navegador | B17: 124
A20: Cómo usar esta Excel
C21: http://olgacarreras.blogspot.com/2011/07/sirius-nueva-sistema-para-la-evaluacion.html
A22: 1. Se recomienda leer primero el artículo dónde se explica el nuevo sistema de evaluación Sirius:
A23: 2. Rellenar los datos generales del sitio a evaluar (en esta pestaña)
A24: 3. Evaluar los criterios de cada heurístico (10, uno por pestaña) según las indicaciones que se incluyen en cada pestaña
A25: 4. En la pestaña "Cálculo de % de usabilidad" se puede consultar la puntuación que recibe el sitio (pocentaje: 0-100) según la evaluación que se ha hecho de los diferentes criterios
A27: Licencia
A29: Esta excel se distribuye gratuitamente. Está protegida para evitar versiones erróneas.
A30: Si deseas colaborar en su mejora o reportar una sugerencia o incedencia puedes enviar un correo a: | C30: carreras.olga@gmail.com

Sheet 1, Aspectos generales
A1: CRITERIOS DEL "HEURÍSTICO ASPECTOS GENERALES": Elementos relacionados con los objetivos del sitio, el look & feel, coherencia y nivel de actualización de contenidos.
A2: Código | B2: Criterio | C2: Valor | D2: Relevancia | E2: Comentarios | F2: Valor interno(vc) | G2: Valor interno de relevancia (rc) | H2: Factor de corrección (fc) | I2: Valor parcial | J2: Valor parcial 2
A3: AG1 | B3: Objetivos del sitio web concretos y bien definidos | C3: 10 | D3: =IF(OR(TipoDeSitio="",C3="NA"),"",VLOOKUP(CONCATENATE(A3,": ",B3),Tabla621,MATCH(TipoDeSitio,Tipos,0)+1,0)) | E3: Los objetivos del servicio de traslados están claramente indicados en la landing. | F3: =IF(C3="","",VLOOKUP(C3,ValoresVC,2,0)) | G3: =IF(D3="","",VLOOKUP($D3,ValoresRC,2,0)) | H3: =IF(OR(G3="",G3=0,'Cálculo de % usabilidad'!$F$5=0),"",G3/'Cálculo de % usabilidad'!$F$5) | I3: =IF(OR(H3="",F3=""),"",H3*F3) | J3: =IF(H3="","",H3*10)
A4: AG2 | B4: Contenidos y servicios ofrecidos precisos y completos | C4: 10 | D4: =IF(OR(TipoDeSitio="",C4="NA"),"",VLOOKUP(CONCATENATE(A4,": ",B4),Tabla621,MATCH(TipoDeSitio,Tipos,0)+1,0)) | E4: Formulario de reserva, gestión y contacto cubren el flujo completo. | F4: =IF(C4="","",VLOOKUP(C4,ValoresVC,2,0)) | G4: =IF(D4="","",VLOOKUP($D4,ValoresRC,2,0)) | H4: =IF(OR(G4="",G4=0,'Cálculo de % usabilidad'!$F$5=0),"",G4/'Cálculo de % usabilidad'!$F$5) | I4: =IF(OR(H4="",F4=""),"",H4*F4) | J4: =IF(H4="","",H4*10)
A5: AG3 | B5: Estructura general del sitio web orientada al usuario | C5: 10 | D5: =IF(OR(TipoDeSitio="",C5="NA"),"",VLOOKUP(CONCATENATE(A5,": ",B5),Tabla621,MATCH(TipoDeSitio,Tipos,0)+1,0)) | E5: Menú global con 4 secciones lógicas: Inicio, Reservar, Mis Reservas, Contacto. | F5: =IF(C5="","",VLOOKUP(C5,ValoresVC,2,0)) | G5: =IF(D5="","",VLOOKUP($D5,ValoresRC,2,0)) | H5: =IF(OR(G5="",G5=0,'Cálculo de % usabilidad'!$F$5=0),"",G5/'Cálculo de % usabilidad'!$F$5) | I5: =IF(OR(H5="",F5=""),"",H5*F5) | J5: =IF(H5="","",H5*10)
A6: AG4 | B6: Look & Feel general se corresponde con los objetivos, características, contenidos y servicios del sitio web | C6: 10 | D6: =IF(OR(TipoDeSitio="",C6="NA"),"",VLOOKUP(CONCATENATE(A6,": ",B6),Tabla621,MATCH(TipoDeSitio,Tipos,0)+1,0)) | E6: Estética de transporte profesional con Bootstrap azul corporativo. | F6: =IF(C6="","",VLOOKUP(C6,ValoresVC,2,0)) | G6: =IF(D6="","",VLOOKUP($D6,ValoresRC,2,0)) | H6: =IF(OR(G6="",G6=0,'Cálculo de % usabilidad'!$F$5=0),"",G6/'Cálculo de % usabilidad'!$F$5) | I6: =IF(OR(H6="",F6=""),"",H6*F6) | J6: =IF(H6="","",H6*10)
A7: AG5 | B7: Diseño general del sitio web reconocible | C7: 10 | D7: =IF(OR(TipoDeSitio="",C7="NA"),"",VLOOKUP(CONCATENATE(A7,": ",B7),Tabla621,MATCH(TipoDeSitio,Tipos,0)+1,0)) | E7: Logo de taxi + nombre de marca visible en todas las páginas. | F7: =IF(C7="","",VLOOKUP(C7,ValoresVC,2,0)) | G7: =IF(D7="","",VLOOKUP($D7,ValoresRC,2,0)) | H7: =IF(OR(G7="",G7=0,'Cálculo de % usabilidad'!$F$5=0),"",G7/'Cálculo de % usabilidad'!$F$5) | I7: =IF(OR(H7="",F7=""),"",H7*F7) | J7: =IF(H7="","",H7*10)
A8: AG6 | B8: Diseño general del sitio web coherente | C8: 10 | D8: =IF(OR(TipoDeSitio="",C8="NA"),"",VLOOKUP(CONCATENATE(A8,": ",B8),Tabla621,MATCH(TipoDeSitio,Tipos,0)+1,0)) | E8: Navbar, tipografía y paleta de color consistentes en todas las páginas. | F8: =IF(C8="","",VLOOKUP(C8,ValoresVC,2,0)) | G8: =IF(D8="","",VLOOKUP($D8,ValoresRC,2,0)) | H8: =IF(OR(G8="",G8=0,'Cálculo de % usabilidad'!$F$5=0),"",G8/'Cálculo de % usabilidad'!$F$5) | I8: =IF(OR(H8="",F8=""),"",H8*F8) | J8: =IF(H8="","",H8*10)
A9: AG7 | B9: Se utiliza el idioma del usuario | C9: 10 | D9: =IF(OR(TipoDeSitio="",C9="NA"),"",VLOOKUP(CONCATENATE(A9,": ",B9),Tabla621,MATCH(TipoDeSitio,Tipos,0)+1,0)) | E9: Todo el contenido está en español. | F9: =IF(C9="","",VLOOKUP(C9,ValoresVC,2,0)) | G9: =IF(D9="","",VLOOKUP($D9,ValoresRC,2,0)) | H9: =IF(OR(G9="",G9=0,'Cálculo de % usabilidad'!$F$5=0),"",G9/'Cálculo de % usabilidad'!$F$5) | I9: =IF(OR(H9="",F9=""),"",H9*F9) | J9: =IF(H9="","",H9*10)
A10: AG8 | B10: Se da soporte a otro/s idioma/s | C10: 10 | D10: =IF(OR(TipoDeSitio="",C10="NA"),"",VLOOKUP(CONCATENATE(A10,": ",B10),Tabla621,MATCH(TipoDeSitio,Tipos,0)+1,0)) | E10: Botón de cambio de idioma (lang-toggle) en la barra de navegación. | F10: =IF(C10="","",VLOOKUP(C10,ValoresVC,2,0)) | G10: =IF(D10="","",VLOOKUP($D10,ValoresRC,2,0)) | H10: =IF(OR(G10="",G10=0,'Cálculo de % usabilidad'!$F$5=0),"",G10/'Cálculo de % usabilidad'!$F$5) | I10: =IF(OR(H10="",F10=""),"",H10*F10) | J10: =IF(H10="","",H10*10)
A11: AG9 | B11: Traducción del sitio completa y correcta | C11: 10 | D11: =IF(OR(TipoDeSitio="",C11="NA"),"",VLOOKUP(CONCATENATE(A11,": ",B11),Tabla621,MATCH(TipoDeSitio,Tipos,0)+1,0)) | E11: Todos los textos usan atributos data-i18n con traducciones completas. | F11: =IF(C11="","",VLOOKUP(C11,ValoresVC,2,0)) | G11: =IF(D11="","",VLOOKUP($D11,ValoresRC,2,0)) | H11: =IF(OR(G11="",G11=0,'Cálculo de % usabilidad'!$F$5=0),"",G11/'Cálculo de % usabilidad'!$F$5) | I11: =IF(OR(H11="",F11=""),"",H11*F11) | J11: =IF(H11="","",H11*10)
A12: AG10 | B12: Sitio web actualizado periódicamente | C12: NA | D12: =IF(OR(TipoDeSitio="",C12="NA"),"",VLOOKUP(CONCATENATE(A12,": ",B12),Tabla621,MATCH(TipoDeSitio,Tipos,0)+1,0)) | E12: Es un prototipo estático; no hay historial de actualizaciones. | F12: =IF(C12="","",VLOOKUP(C12,ValoresVC,2,0)) | G12: =IF(D12="","",VLOOKUP($D12,ValoresRC,2,0)) | H12: =IF(OR(G12="",G12=0,'Cálculo de % usabilidad'!$F$5=0),"",G12/'Cálculo de % usabilidad'!$F$5) | I12: =IF(OR(H12="",F12=""),"",H12*F12) | J12: =IF(H12="","",H12*10) | K12: Núm.elementos evaluados | L12: =10-(COUNTIF(C3:C12,"NA")+COUNTBLANK(C3:C12)) | M12: (no contabiliza ni los vacíos ni los NA)
G13: =IF(SUM(G3:G12)=0,"",SUM(G3:G12))
A14: Instrucciones | C14: Leyenda Valor
A15: 1. Evalue cada criterio y rellene la columna "Valor" según la leyenda | C15: 0 | D15: No se cumple en absoluto | F15: NEP | G15: No se cumple en los enlaces principales
A16: 2. Añada sus comentarios o la referencia a los mismos en otro documento anexo en la columna "Comentarios" | C16: 10 | D16: Se cumple totalmente | F16: NPP | G16: No se cumple en la página principal
C17: NA | D17: Criterio no aplicable en el sitio | F17: NPI | G17: No se cumple en alguna página interior
C18: NTS | D18: No se cumple en todo el sitio | F18: S | G18: Se cumple el criterio

Sheet 2, Identidad e Información
A1: CRITERIOS DEL "IDENTIDAD E INFORMACIÓN": Elementos relacionados con la identidad del sitio, la información proporcionada sobre el proveedor y la autoría de los contenidos.
A2: Código | B2: Criterio | C2: Valor | D2: Relevancia | E2: Comentarios | F2: Valor interno(vc) | G2: Valor interno de relevancia (rc) | H2: Factor de corrección (fc) | I2: Valor parcial | J2: Valor parcial 2
A3: II.1 | B3: Identidad o logotipo significativo, identificable y suficientemente visible | C3: 10 | D3: =IF(OR(TipoDeSitio="",C3="NA"),"",VLOOKUP(CONCATENATE(A3,": ",B3),Tabla622,MATCH(TipoDeSitio,Tipos,0)+1,0)) | E3: Logo SVG de taxi + nombre "Taxi Transfer Tenerife" en la barra superior. | F3: =IF(C3="","",VLOOKUP(C3,ValoresVC,2,0)) | G3: =IF(D3="","",VLOOKUP($D3,ValoresRC,2,0)) | H3: =IF(OR(G3="",G3=0,'Cálculo de % usabilidad'!$F$5=0),"",G3/'Cálculo de % usabilidad'!$F$5) | I3: =IF(OR(H3="",F3=""),"",H3*F3) | J3: =IF(H3="","",H3*10)
A4: II.2 | B4: Identidad del sitio en todas las páginas | C4: 10 | D4: =IF(OR(TipoDeSitio="",C4="NA"),"",VLOOKUP(CONCATENATE(A4,": ",B4),Tabla622,MATCH(TipoDeSitio,Tipos,0)+1,0)) | E4: Navbar fija con logo y nombre en todas las páginas. | F4: =IF(C4="","",VLOOKUP(C4,ValoresVC,2,0)) | G4: =IF(D4="","",VLOOKUP($D4,ValoresRC,2,0)) | H4: =IF(OR(G4="",G4=0,'Cálculo de % usabilidad'!$F$5=0),"",G4/'Cálculo de % usabilidad'!$F$5) | I4: =IF(OR(H4="",F4=""),"",H4*F4) | J4: =IF(H4="","",H4*10)
A5: II.3 | B5: Eslogan o tagline adecuado al objetivo del sitio | C5: 10 | D5: =IF(OR(TipoDeSitio="",C5="NA"),"",VLOOKUP(CONCATENATE(A5,": ",B5),Tabla622,MATCH(TipoDeSitio,Tipos,0)+1,0)) | E5: "Traslados desde el Aeropuerto de Tenerife Sur" en la sección hero. | F5: =IF(C5="","",VLOOKUP(C5,ValoresVC,2,0)) | G5: =IF(D5="","",VLOOKUP($D5,ValoresRC,2,0)) | H5: =IF(OR(G5="",G5=0,'Cálculo de % usabilidad'!$F$5=0),"",G5/'Cálculo de % usabilidad'!$F$5) | I5: =IF(OR(H5="",F5=""),"",H5*F5) | J5: =IF(H5="","",H5*10)
A6: II.4 | B6: Se ofrece información sobre el sitio web, empresa | C6: 8 | D6: =IF(OR(TipoDeSitio="",C6="NA"),"",VLOOKUP(CONCATENATE(A6,": ",B6),Tabla622,MATCH(TipoDeSitio,Tipos,0)+1,0)) | E6: Página de contacto incluye dirección, teléfono y email corporativo. | F6: =IF(C6="","",VLOOKUP(C6,ValoresVC,2,0)) | G6: =IF(D6="","",VLOOKUP($D6,ValoresRC,2,0)) | H6: =IF(OR(G6="",G6=0,'Cálculo de % usabilidad'!$F$5=0),"",G6/'Cálculo de % usabilidad'!$F$5) | I6: =IF(OR(H6="",F6=""),"",H6*F6) | J6: =IF(H6="","",H6*10)
A7: II.5 | B7: Existen mecanismos de contacto | C7: 10 | D7: =IF(OR(TipoDeSitio="",C7="NA"),"",VLOOKUP(CONCATENATE(A7,": ",B7),Tabla622,MATCH(TipoDeSitio,Tipos,0)+1,0)) | E7: Página de contacto con formulario, tel: y mailto: clicables. | F7: =IF(C7="","",VLOOKUP(C7,ValoresVC,2,0)) | G7: =IF(D7="","",VLOOKUP($D7,ValoresRC,2,0)) | H7: =IF(OR(G7="",G7=0,'Cálculo de % usabilidad'!$F$5=0),"",G7/'Cálculo de % usabilidad'!$F$5) | I7: =IF(OR(H7="",F7=""),"",H7*F7) | J7: =IF(H7="","",H7*10)
A8: II.6 | B8: Se ofrece información sobre la protección de datos de carácter personal o los derechos de autor de los contenidos del sitio web | C8: 0 | D8: =IF(OR(TipoDeSitio="",C8="NA"),"",VLOOKUP(CONCATENATE(A8,": ",B8),Tabla622,MATCH(TipoDeSitio,Tipos,0)+1,0)) | E8: No existe enlace a Política de Privacidad ni aviso legal. | F8: =IF(C8="","",VLOOKUP(C8,ValoresVC,2,0)) | G8: =IF(D8="","",VLOOKUP($D8,ValoresRC,2,0)) | H8: =IF(OR(G8="",G8=0,'Cálculo de % usabilidad'!$F$5=0),"",G8/'Cálculo de % usabilidad'!$F$5) | I8: =IF(OR(H8="",F8=""),"",H8*F8) | J8: =IF(H8="","",H8*10)
A9: II.7 | B9: Se ofrece información sobre el autor, fuentes y fechas de creación y revisión en artículos, noticias, informes | C9: NA | D9: =IF(OR(TipoDeSitio="",C9="NA"),"",VLOOKUP(CONCATENATE(A9,": ",B9),Tabla622,MATCH(TipoDeSitio,Tipos,0)+1,0)) | E9: El sitio no publica artículos ni noticias. | F9: =IF(C9="","",VLOOKUP(C9,ValoresVC,2,0)) | G9: =IF(D9="","",VLOOKUP($D9,ValoresRC,2,0)) | H9: =IF(OR(G9="",G9=0,'Cálculo de % usabilidad'!$F$5=0),"",G9/'Cálculo de % usabilidad'!$F$5) | I9: =IF(OR(H9="",F9=""),"",H9*F9) | J9: =IF(H9="","",H9*10) | K9: Núm.elementos evaluados | L9: =7-(COUNTIF(C3:C9,"NA")+COUNTBLANK(C3:C9)) | M9: (no contabiliza ni los vacíos ni los NA)
G10: =IF(SUM(G3:G9)=0,"",SUM(G3:G9))
A11: Instrucciones | C11: Leyenda Valor
A12: 1. Evalue cada criterio y rellene la columna "Valor" según la leyenda | C12: 0 | D12: No se cumple en absoluto | F12: NEP | G12: No se cumple en los enlaces principales
A13: 2. Añada sus comentarios o la referencia a los mismos en otro documento anexo en la columna "Comentarios" | C13: 10 | D13: Se cumple totalmente | F13: NPP | G13: No se cumple en la página principal
C14: NA | D14: Criterio no aplicable en el sitio | F14: NPI | G14: No se cumple en alguna página interior
C15: NTS | D15: No se cumple en todo el sitio | F15: S | G15: Se cumple el criterio

Sheet 3, Estructura y navegación
A1: CRITERIOS DEL "ESTRUCTURA Y NAVEGACIÓN": Elementos relacionados con la idoneidad de la arquitectura de la información y la navegación del sitio.
A2: Código | B2: Criterio | C2: Valor | D2: Relevancia | E2: Comentarios | F2: Valor interno(vc) | G2: Valor interno de relevancia (rc) | H2: Factor de corrección (fc) | I2: Valor parcial | J2: Valor parcial 2
A3: EN.1 | B3: Se ha evitado pantalla de bienvenida | C3: 10 | D3: =IF(OR(TipoDeSitio="",C3="NA"),"",VLOOKUP(CONCATENATE(A3,": ",B3),Tabla623,MATCH(TipoDeSitio,Tipos,0)+1,0)) | E3: El sitio abre directamente en la landing sin pantalla intermedia. | F3: =IF(C3="","",VLOOKUP(C3,ValoresVC,2,0)) | G3: =IF(D3="","",VLOOKUP($D3,ValoresRC,2,0)) | H3: =IF(OR(G3="",G3=0,'Cálculo de % usabilidad'!$F$5=0),"",G3/'Cálculo de % usabilidad'!$F$5) | I3: =IF(OR(H3="",F3=""),"",H3*F3) | J3: =IF(H3="","",H3*10)
A4: EN.2 | B4: Estructura de organización y navegación adecuada | C4: 10 | D4: =IF(OR(TipoDeSitio="",C4="NA"),"",VLOOKUP(CONCATENATE(A4,": ",B4),Tabla623,MATCH(TipoDeSitio,Tipos,0)+1,0)) | E4: Flujo lineal: inicio → reserva → confirmación → pago → gestión. | F4: =IF(C4="","",VLOOKUP(C4,ValoresVC,2,0)) | G4: =IF(D4="","",VLOOKUP($D4,ValoresRC,2,0)) | H4: =IF(OR(G4="",G4=0,'Cálculo de % usabilidad'!$F$5=0),"",G4/'Cálculo de % usabilidad'!$F$5) | I4: =IF(OR(H4="",F4=""),"",H4*F4) | J4: =IF(H4="","",H4*10)
A5: EN.3 | B5: Organización de elementos consistente con las convenciones | C5: 10 | D5: =IF(OR(TipoDeSitio="",C5="NA"),"",VLOOKUP(CONCATENATE(A5,": ",B5),Tabla623,MATCH(TipoDeSitio,Tipos,0)+1,0)) | E5: Navbar fija con convención estándar Bootstrap en la parte superior. | F5: =IF(C5="","",VLOOKUP(C5,ValoresVC,2,0)) | G5: =IF(D5="","",VLOOKUP($D5,ValoresRC,2,0)) | H5: =IF(OR(G5="",G5=0,'Cálculo de % usabilidad'!$F$5=0),"",G5/'Cálculo de % usabilidad'!$F$5) | I5: =IF(OR(H5="",F5=""),"",H5*F5) | J5: =IF(H5="","",H5*10)
A6: EN.4 | B6: Control del número de elementos y de términos por elemento en los menús de navegación | C6: 10 | D6: =IF(OR(TipoDeSitio="",C6="NA"),"",VLOOKUP(CONCATENATE(A6,": ",B6),Tabla623,MATCH(TipoDeSitio,Tipos,0)+1,0)) | E6: Menú con exactamente 4 elementos: Inicio, Reservar, Mis Reservas, Contacto. | F6: =IF(C6="","",VLOOKUP(C6,ValoresVC,2,0)) | G6: =IF(D6="","",VLOOKUP($D6,ValoresRC,2,0)) | H6: =IF(OR(G6="",G6=0,'Cálculo de % usabilidad'!$F$5=0),"",G6/'Cálculo de % usabilidad'!$F$5) | I6: =IF(OR(H6="",F6=""),"",H6*F6) | J6: =IF(H6="","",H6*10)
A7: EN.5 | B7: Equilibrio entre profundidad y anchura en el caso de estructura jerárquica | C7: 10 | D7: =IF(OR(TipoDeSitio="",C7="NA"),"",VLOOKUP(CONCATENATE(A7,": ",B7),Tabla623,MATCH(TipoDeSitio,Tipos,0)+1,0)) | E7: Jerarquía de un nivel de profundidad; todos los destinos accesibles desde la landing. | F7: =IF(C7="","",VLOOKUP(C7,ValoresVC,2,0)) | G7: =IF(D7="","",VLOOKUP($D7,ValoresRC,2,0)) | H7: =IF(OR(G7="",G7=0,'Cálculo de % usabilidad'!$F$5=0),"",G7/'Cálculo de % usabilidad'!$F$5) | I7: =IF(OR(H7="",F7=""),"",H7*F7) | J7: =IF(H7="","",H7*10)
A8: EN.6 | B8: Enlaces fácilmente reconocibles como tales | C8: 10 | D8: =IF(OR(TipoDeSitio="",C8="NA"),"",VLOOKUP(CONCATENATE(A8,": ",B8),Tabla623,MATCH(TipoDeSitio,Tipos,0)+1,0)) | E8: Los enlaces de navegación son texto azul subrayado y botones Bootstrap estándar. | F8: =IF(C8="","",VLOOKUP(C8,ValoresVC,2,0)) | G8: =IF(D8="","",VLOOKUP($D8,ValoresRC,2,0)) | H8: =IF(OR(G8="",G8=0,'Cálculo de % usabilidad'!$F$5=0),"",G8/'Cálculo de % usabilidad'!$F$5) | I8: =IF(OR(H8="",F8=""),"",H8*F8) | J8: =IF(H8="","",H8*10)
A9: EN.7 | B9: La caracterización de los enlaces indica su estado (visitados, activos) | C9: 10 | D9: =IF(OR(TipoDeSitio="",C9="NA"),"",VLOOKUP(CONCATENATE(A9,": ",B9),Tabla623,MATCH(TipoDeSitio,Tipos,0)+1,0)) | E9: Atributo aria-current="page" y clase CSS "active" en el ítem actual del menú. | F9: =IF(C9="","",VLOOKUP(C9,ValoresVC,2,0)) | G9: =IF(D9="","",VLOOKUP($D9,ValoresRC,2,0)) | H9: =IF(OR(G9="",G9=0,'Cálculo de % usabilidad'!$F$5=0),"",G9/'Cálculo de % usabilidad'!$F$5) | I9: =IF(OR(H9="",F9=""),"",H9*F9) | J9: =IF(H9="","",H9*10)
A10: EN.8 | B10: No hay redundancia de enlaces | C10: 10 | D10: =IF(OR(TipoDeSitio="",C10="NA"),"",VLOOKUP(CONCATENATE(A10,": ",B10),Tabla623,MATCH(TipoDeSitio,Tipos,0)+1,0)) | E10: No existen duplicidades de enlace dentro de los menús de navegación. | F10: =IF(C10="","",VLOOKUP(C10,ValoresVC,2,0)) | G10: =IF(D10="","",VLOOKUP($D10,ValoresRC,2,0)) | H10: =IF(OR(G10="",G10=0,'Cálculo de % usabilidad'!$F$5=0),"",G10/'Cálculo de % usabilidad'!$F$5) | I10: =IF(OR(H10="",F10=""),"",H10*F10) | J10: =IF(H10="","",H10*10)
A11: EN.9 | B11: No hay enlaces rotos | C11: 10 | D11: =IF(OR(TipoDeSitio="",C11="NA"),"",VLOOKUP(CONCATENATE(A11,": ",B11),Tabla623,MATCH(TipoDeSitio,Tipos,0)+1,0)) | E11: Todos los href apuntan a páginas existentes dentro del prototipo. | F11: =IF(C11="","",VLOOKUP(C11,ValoresVC,2,0)) | G11: =IF(D11="","",VLOOKUP($D11,ValoresRC,2,0)) | H11: =IF(OR(G11="",G11=0,'Cálculo de % usabilidad'!$F$5=0),"",G11/'Cálculo de % usabilidad'!$F$5) | I11: =IF(OR(H11="",F11=""),"",H11*F11) | J11: =IF(H11="","",H11*10)
A12: EN.10 | B12: No hay enlaces que lleven a la misma página que se está visualizando | C12: 10 | D12: =IF(OR(TipoDeSitio="",C12="NA"),"",VLOOKUP(CONCATENATE(A12,": ",B12),Tabla623,MATCH(TipoDeSitio,Tipos,0)+1,0)) | E12: La página activa no tiene enlace a sí misma (marcada como activa). | F12: =IF(C12="","",VLOOKUP(C12,ValoresVC,2,0)) | G12: =IF(D12="","",VLOOKUP($D12,ValoresRC,2,0)) | H12: =IF(OR(G12="",G12=0,'Cálculo de % usabilidad'!$F$5=0),"",G12/'Cálculo de % usabilidad'!$F$5) | I12: =IF(OR(H12="",F12=""),"",H12*F12) | J12: =IF(H12="","",H12*10)
A13: EN.11 | B13: En las imágenes de enlace se indica el contenido al que se va a acceder | C13: 10 | D13: =IF(OR(TipoDeSitio="",C13="NA"),"",VLOOKUP(CONCATENATE(A13,": ",B13),Tabla623,MATCH(TipoDeSitio,Tipos,0)+1,0)) | E13: Logo SVG tiene alt="Taxi logo"; tarjetas de destino tienen aria-label descriptivo. | F13: =IF(C13="","",VLOOKUP(C13,ValoresVC,2,0)) | G13: =IF(D13="","",VLOOKUP($D13,ValoresRC,2,0)) | H13: =IF(OR(G13="",G13=0,'Cálculo de % usabilidad'!$F$5=0),"",G13/'Cálculo de % usabilidad'!$F$5) | I13: =IF(OR(H13="",F13=""),"",H13*F13) | J13: =IF(H13="","",H13*10)
A14: EN.12 | B14: Existe un enlace para volver al inicio en cada página | C14: 10 | D14: =IF(OR(TipoDeSitio="",C14="NA"),"",VLOOKUP(CONCATENATE(A14,": ",B14),Tabla623,MATCH(TipoDeSitio,Tipos,0)+1,0)) | E14: El logotipo y el enlace de marca apuntan siempre a index.html. | F14: =IF(C14="","",VLOOKUP(C14,ValoresVC,2,0)) | G14: =IF(D14="","",VLOOKUP($D14,ValoresRC,2,0)) | H14: =IF(OR(G14="",G14=0,'Cálculo de % usabilidad'!$F$5=0),"",G14/'Cálculo de % usabilidad'!$F$5) | I14: =IF(OR(H14="",F14=""),"",H14*F14) | J14: =IF(H14="","",H14*10)
A15: EN.13 | B15: Existen elementos de navegación que orienten al usuario acerca de dónde está y cómo deshacer su navegación (ej: migas) | C15: 5 | D15: =IF(OR(TipoDeSitio="",C15="NA"),"",VLOOKUP(CONCATENATE(A15,": ",B15),Tabla623,MATCH(TipoDeSitio,Tipos,0)+1,0)) | E15: El menú marca la página activa con aria-current y clase CSS "active", pero no hay migas de pan (breadcrumbs) explícitas. | F15: =IF(C15="","",VLOOKUP(C15,ValoresVC,2,0)) | G15: =IF(D15="","",VLOOKUP($D15,ValoresRC,2,0)) | H15: =IF(OR(G15="",G15=0,'Cálculo de % usabilidad'!$F$5=0),"",G15/'Cálculo de % usabilidad'!$F$5) | I15: =IF(OR(H15="",F15=""),"",H15*F15) | J15: =IF(H15="","",H15*10)
A16: EN.14 | B16: Existe mapa del sitio para acceder directamente a los contenidos sin navegar | C16: 0 | D16: =IF(OR(TipoDeSitio="",C16="NA"),"",VLOOKUP(CONCATENATE(A16,": ",B16),Tabla623,MATCH(TipoDeSitio,Tipos,0)+1,0)) | E16: No existe mapa del sitio. El sitio tiene solo 4 páginas por lo que su necesidad es baja, pero no está implementado. | F16: =IF(C16="","",VLOOKUP(C16,ValoresVC,2,0)) | G16: =IF(D16="","",VLOOKUP($D16,ValoresRC,2,0)) | H16: =IF(OR(G16="",G16=0,'Cálculo de % usabilidad'!$F$5=0),"",G16/'Cálculo de % usabilidad'!$F$5) | I16: =IF(OR(H16="",F16=""),"",H16*F16) | J16: =IF(H16="","",H16*10) | K16: Núm.elementos evaluados | L16: =14-(COUNTIF(C3:C16,"NA")+COUNTBLANK(C3:C16)) | M16: (no contabiliza ni los vacíos ni los NA)
G17: =IF(SUM(G3:G16)=0,"",SUM(G3:G16))
A18: Instrucciones | C18: Leyenda Valor
A19: 1. Evalue cada criterio y rellene la columna "Valor" según la leyenda | C19: 0 | D19: No se cumple en absoluto | F19: NEP | G19: No se cumple en los enlaces principales
A20: 2. Añada sus comentarios o la referencia a los mismos en otro documento anexo en la columna "Comentarios" | C20: 10 | D20: Se cumple totalmente | F20: NPP | G20: No se cumple en la página principal
C21: NA | D21: Criterio no aplicable en el sitio | F21: NPI | G21: No se cumple en alguna página interior
C22: NTS | D22: No se cumple en todo el sitio | F22: S | G22: Se cumple el criterio

Sheet 4, Rotulado
A1: CRITERIOS DEL "ROTULADO": Elementos relacionados con la significación, corrección y familiaridad del rotulado de los contenidos.
A2: Código | B2: Criterio | C2: Valor | D2: Relevancia | E2: Comentarios | F2: Valor interno(vc) | G2: Valor interno de relevancia (rc) | H2: Factor de corrección (fc) | I2: Valor parcial | J2: Valor parcial 2
A3: RO.1 | B3: Rótulos significativos | C3: 10 | D3: =IF(OR(TipoDeSitio="",C3="NA"),"",VLOOKUP(CONCATENATE(A3,": ",B3),Tabla624,MATCH(TipoDeSitio,Tipos,0)+1,0)) | E3: Los rótulos de sección (Reservar, Mis Reservas, Contacto) son autoexplicativos. | F3: =IF(C3="","",VLOOKUP(C3,ValoresVC,2,0)) | G3: =IF(D3="","",VLOOKUP($D3,ValoresRC,2,0)) | H3: =IF(OR(G3="",G3=0,'Cálculo de % usabilidad'!$F$5=0),"",G3/'Cálculo de % usabilidad'!$F$5) | I3: =IF(OR(H3="",F3=""),"",H3*F3) | J3: =IF(H3="","",H3*10)
A4: RO.2 | B4: Sistema de rotulado controlado y preciso | C4: 10 | D4: =IF(OR(TipoDeSitio="",C4="NA"),"",VLOOKUP(CONCATENATE(A4,": ",B4),Tabla624,MATCH(TipoDeSitio,Tipos,0)+1,0)) | E4: Nomenclatura coherente en etiquetas de formulario y navegación. | F4: =IF(C4="","",VLOOKUP(C4,ValoresVC,2,0)) | G4: =IF(D4="","",VLOOKUP($D4,ValoresRC,2,0)) | H4: =IF(OR(G4="",G4=0,'Cálculo de % usabilidad'!$F$5=0),"",G4/'Cálculo de % usabilidad'!$F$5) | I4: =IF(OR(H4="",F4=""),"",H4*F4) | J4: =IF(H4="","",H4*10)
A5: RO.3 | B5: Título de las páginas, correcto y planificado | C5: 10 | D5: =IF(OR(TipoDeSitio="",C5="NA"),"",VLOOKUP(CONCATENATE(A5,": ",B5),Tabla624,MATCH(TipoDeSitio,Tipos,0)+1,0)) | E5: Cada página tiene <title> específico: "Reserva tu Traslado", "Contacto", etc. | F5: =IF(C5="","",VLOOKUP(C5,ValoresVC,2,0)) | G5: =IF(D5="","",VLOOKUP($D5,ValoresRC,2,0)) | H5: =IF(OR(G5="",G5=0,'Cálculo de % usabilidad'!$F$5=0),"",G5/'Cálculo de % usabilidad'!$F$5) | I5: =IF(OR(H5="",F5=""),"",H5*F5) | J5: =IF(H5="","",H5*10)
A6: RO.4 | B6: URL página principal correcta, clara y fácil de recordar | C6: NA | D6: =IF(OR(TipoDeSitio="",C6="NA"),"",VLOOKUP(CONCATENATE(A6,": ",B6),Tabla624,MATCH(TipoDeSitio,Tipos,0)+1,0)) | E6: Es un prototipo local sin URL pública. | F6: =IF(C6="","",VLOOKUP(C6,ValoresVC,2,0)) | G6: =IF(D6="","",VLOOKUP($D6,ValoresRC,2,0)) | H6: =IF(OR(G6="",G6=0,'Cálculo de % usabilidad'!$F$5=0),"",G6/'Cálculo de % usabilidad'!$F$5) | I6: =IF(OR(H6="",F6=""),"",H6*F6) | J6: =IF(H6="","",H6*10)
A7: RO.5 | B7: URLs de páginas internas claras | C7: 10 | D7: =IF(OR(TipoDeSitio="",C7="NA"),"",VLOOKUP(CONCATENATE(A7,": ",B7),Tabla624,MATCH(TipoDeSitio,Tipos,0)+1,0)) | E7: Archivos: booking.html, manage-booking.html, contact.html, payment.html. | F7: =IF(C7="","",VLOOKUP(C7,ValoresVC,2,0)) | G7: =IF(D7="","",VLOOKUP($D7,ValoresRC,2,0)) | H7: =IF(OR(G7="",G7=0,'Cálculo de % usabilidad'!$F$5=0),"",G7/'Cálculo de % usabilidad'!$F$5) | I7: =IF(OR(H7="",F7=""),"",H7*F7) | J7: =IF(H7="","",H7*10)
A8: RO.6 | B8: URLs de páginas internas permanentes | C8: NA | D8: =IF(OR(TipoDeSitio="",C8="NA"),"",VLOOKUP(CONCATENATE(A8,": ",B8),Tabla624,MATCH(TipoDeSitio,Tipos,0)+1,0)) | E8: Prototipo estático sin URLs de producción. | F8: =IF(C8="","",VLOOKUP(C8,ValoresVC,2,0)) | G8: =IF(D8="","",VLOOKUP($D8,ValoresRC,2,0)) | H8: =IF(OR(G8="",G8=0,'Cálculo de % usabilidad'!$F$5=0),"",G8/'Cálculo de % usabilidad'!$F$5) | I8: =IF(OR(H8="",F8=""),"",H8*F8) | J8: =IF(H8="","",H8*10) | K8: Núm.elementos evaluados | L8: =6-(COUNTIF(C3:C8,"NA")+COUNTBLANK(C3:C8)) | M8: (no contabiliza ni los vacíos ni los NA)
G9: =IF(SUM(G3:G8)=0,"",SUM(G3:G8))
A10: Instrucciones | C10: Leyenda Valor
A11: 1. Evalue cada criterio y rellene la columna "Valor" según la leyenda | C11: 0 | D11: No se cumple en absoluto | F11: NEP | G11: No se cumple en los enlaces principales
A12: 2. Añada sus comentarios o la referencia a los mismos en otro documento anexo en la columna "Comentarios" | C12: 10 | D12: Se cumple totalmente | F12: NPP | G12: No se cumple en la página principal
C13: NA | D13: Criterio no aplicable en el sitio | F13: NPI | G13: No se cumple en alguna página interior
C14: NTS | D14: No se cumple en todo el sitio | F14: S | G14: Se cumple el criterio

Sheet 5, Layout de la página
A1: CRITERIOS DEL "LAYOUT DE LA PÁGINA": Elementos relacionados con la distribución y el aspecto de los elementos de navegación e información en la interfaz
A2: Código | B2: Criterio | C2: Valor | D2: Relevancia | E2: Comentarios | F2: Valor interno(vc) | G2: Valor interno de relevancia (rc) | H2: Factor de corrección (fc) | I2: Valor parcial | J2: Valor parcial 2
A3: LA.1 | B3: Se aprovechan las zonas de alta jerarquía informativa de la página para contenidos de mayor relevancia | C3: 10 | D3: =IF(OR(TipoDeSitio="",C3="NA"),"",VLOOKUP(CONCATENATE(A3,": ",B3),Tabla625,MATCH(TipoDeSitio,Tipos,0)+1,0)) | E3: Hero section en la zona superior con CTA principal y título h1. | F3: =IF(C3="","",VLOOKUP(C3,ValoresVC,2,0)) | G3: =IF(D3="","",VLOOKUP($D3,ValoresRC,2,0)) | H3: =IF(OR(G3="",G3=0,'Cálculo de % usabilidad'!$F$5=0),"",G3/'Cálculo de % usabilidad'!$F$5) | I3: =IF(OR(H3="",F3=""),"",H3*F3) | J3: =IF(H3="","",H3*10)
A4: LA.2 | B4: Se ha evitado la sobrecarga informativa | C4: 10 | D4: =IF(OR(TipoDeSitio="",C4="NA"),"",VLOOKUP(CONCATENATE(A4,": ",B4),Tabla625,MATCH(TipoDeSitio,Tipos,0)+1,0)) | E4: Cada sección contiene un único tema; no hay acumulación de elementos. | F4: =IF(C4="","",VLOOKUP(C4,ValoresVC,2,0)) | G4: =IF(D4="","",VLOOKUP($D4,ValoresRC,2,0)) | H4: =IF(OR(G4="",G4=0,'Cálculo de % usabilidad'!$F$5=0),"",G4/'Cálculo de % usabilidad'!$F$5) | I4: =IF(OR(H4="",F4=""),"",H4*F4) | J4: =IF(H4="","",H4*10)
A5: LA.3 | B5: Es una interfaz limpia, sin ruido visual | C5: 10 | D5: =IF(OR(TipoDeSitio="",C5="NA"),"",VLOOKUP(CONCATENATE(A5,": ",B5),Tabla625,MATCH(TipoDeSitio,Tipos,0)+1,0)) | E5: Bootstrap 5 garantiza layout limpio con separación visual clara. | F5: =IF(C5="","",VLOOKUP(C5,ValoresVC,2,0)) | G5: =IF(D5="","",VLOOKUP($D5,ValoresRC,2,0)) | H5: =IF(OR(G5="",G5=0,'Cálculo de % usabilidad'!$F$5=0),"",G5/'Cálculo de % usabilidad'!$F$5) | I5: =IF(OR(H5="",F5=""),"",H5*F5) | J5: =IF(H5="","",H5*10)
A6: LA.4 | B6: Existen zonas en blanco entre los objetos informativos de la página para poder descansar la vista | C6: 10 | D6: =IF(OR(TipoDeSitio="",C6="NA"),"",VLOOKUP(CONCATENATE(A6,": ",B6),Tabla625,MATCH(TipoDeSitio,Tipos,0)+1,0)) | E6: Uso sistemático de py-5, mb-4, gap-3 para espaciado entre bloques. | F6: =IF(C6="","",VLOOKUP(C6,ValoresVC,2,0)) | G6: =IF(D6="","",VLOOKUP($D6,ValoresRC,2,0)) | H6: =IF(OR(G6="",G6=0,'Cálculo de % usabilidad'!$F$5=0),"",G6/'Cálculo de % usabilidad'!$F$5) | I6: =IF(OR(H6="",F6=""),"",H6*F6) | J6: =IF(H6="","",H6*10)
A7: LA.5 | B7: Uso correcto del espacio visual de la página | C7: 10 | D7: =IF(OR(TipoDeSitio="",C7="NA"),"",VLOOKUP(CONCATENATE(A7,": ",B7),Tabla625,MATCH(TipoDeSitio,Tipos,0)+1,0)) | E7: Grid de 12 columnas Bootstrap con ocupación equilibrada del espacio. | F7: =IF(C7="","",VLOOKUP(C7,ValoresVC,2,0)) | G7: =IF(D7="","",VLOOKUP($D7,ValoresRC,2,0)) | H7: =IF(OR(G7="",G7=0,'Cálculo de % usabilidad'!$F$5=0),"",G7/'Cálculo de % usabilidad'!$F$5) | I7: =IF(OR(H7="",F7=""),"",H7*F7) | J7: =IF(H7="","",H7*10)
A8: LA.6 | B8: Se utiliza correctamente la jerarquía visual para expresar las relaciones del tipo "parte de" entre los elementos de la página | C8: 10 | D8: =IF(OR(TipoDeSitio="",C8="NA"),"",VLOOKUP(CONCATENATE(A8,": ",B8),Tabla625,MATCH(TipoDeSitio,Tipos,0)+1,0)) | E8: Encabezados h1→h2→h3 bien jerarquizados; fieldsets en el formulario. | F8: =IF(C8="","",VLOOKUP(C8,ValoresVC,2,0)) | G8: =IF(D8="","",VLOOKUP($D8,ValoresRC,2,0)) | H8: =IF(OR(G8="",G8=0,'Cálculo de % usabilidad'!$F$5=0),"",G8/'Cálculo de % usabilidad'!$F$5) | I8: =IF(OR(H8="",F8=""),"",H8*F8) | J8: =IF(H8="","",H8*10)
A9: LA.7 | B9: Se ha controlado la longitud de página | C9: 10 | D9: =IF(OR(TipoDeSitio="",C9="NA"),"",VLOOKUP(CONCATENATE(A9,": ",B9),Tabla625,MATCH(TipoDeSitio,Tipos,0)+1,0)) | E9: Las páginas no superan 2-3 pantallas de scroll. | F9: =IF(C9="","",VLOOKUP(C9,ValoresVC,2,0)) | G9: =IF(D9="","",VLOOKUP($D9,ValoresRC,2,0)) | H9: =IF(OR(G9="",G9=0,'Cálculo de % usabilidad'!$F$5=0),"",G9/'Cálculo de % usabilidad'!$F$5) | I9: =IF(OR(H9="",F9=""),"",H9*F9) | J9: =IF(H9="","",H9*10)
A10: LA.8 | B10: La versión impresa de la página es correcta | C10: NA | D10: =IF(OR(TipoDeSitio="",C10="NA"),"",VLOOKUP(CONCATENATE(A10,": ",B10),Tabla625,MATCH(TipoDeSitio,Tipos,0)+1,0)) | E10: No aplica para este prototipo de revisión heurística. | F10: =IF(C10="","",VLOOKUP(C10,ValoresVC,2,0)) | G10: =IF(D10="","",VLOOKUP($D10,ValoresRC,2,0)) | H10: =IF(OR(G10="",G10=0,'Cálculo de % usabilidad'!$F$5=0),"",G10/'Cálculo de % usabilidad'!$F$5) | I10: =IF(OR(H10="",F10=""),"",H10*F10) | J10: =IF(H10="","",H10*10)
A11: LA.9 | B11: El texto de la página se lee sin dificultad | C11: 10 | D11: =IF(OR(TipoDeSitio="",C11="NA"),"",VLOOKUP(CONCATENATE(A11,": ",B11),Tabla625,MATCH(TipoDeSitio,Tipos,0)+1,0)) | E11: Texto en negro sobre fondo blanco/gris claro; contraste adecuado. | F11: =IF(C11="","",VLOOKUP(C11,ValoresVC,2,0)) | G11: =IF(D11="","",VLOOKUP($D11,ValoresRC,2,0)) | H11: =IF(OR(G11="",G11=0,'Cálculo de % usabilidad'!$F$5=0),"",G11/'Cálculo de % usabilidad'!$F$5) | I11: =IF(OR(H11="",F11=""),"",H11*F11) | J11: =IF(H11="","",H11*10)
A12: LA.10 | B12: Se ha evitado el texto parpadeante / deslizante | C12: 10 | D12: =IF(OR(TipoDeSitio="",C12="NA"),"",VLOOKUP(CONCATENATE(A12,": ",B12),Tabla625,MATCH(TipoDeSitio,Tipos,0)+1,0)) | E12: No se usan elementos <blink>, marquee ni animaciones CSS cíclicas. | F12: =IF(C12="","",VLOOKUP(C12,ValoresVC,2,0)) | G12: =IF(D12="","",VLOOKUP($D12,ValoresRC,2,0)) | H12: =IF(OR(G12="",G12=0,'Cálculo de % usabilidad'!$F$5=0),"",G12/'Cálculo de % usabilidad'!$F$5) | I12: =IF(OR(H12="",F12=""),"",H12*F12) | J12: =IF(H12="","",H12*10) | K12: Núm.elementos evaluados | L12: =10-(COUNTIF(C3:C12,"NA")+COUNTBLANK(C3:C12)) | M12: (no contabiliza ni los vacíos ni los NA)
G13: =IF(SUM(G3:G12)=0,"",SUM(G3:G12))
A14: Instrucciones | C14: Leyenda Valor
A15: 1. Evalue cada criterio y rellene la columna "Valor" según la leyenda | C15: 0 | D15: No se cumple en absoluto | F15: NEP | G15: No se cumple en los enlaces principales
A16: 2. Añada sus comentarios o la referencia a los mismos en otro documento anexo en la columna "Comentarios" | C16: 10 | D16: Se cumple totalmente | F16: NPP | G16: No se cumple en la página principal
C17: NA | D17: Criterio no aplicable en el sitio | F17: NPI | G17: No se cumple en alguna página interior
C18: NTS | D18: No se cumple en todo el sitio | F18: S | G18: Se cumple el criterio

Sheet 6, Entendibilidad y Facilidad
A1: CRITERIOS DEL "ENTENDIBILIDAD Y FACILIDAD EN LA INTERACCIÓN": Elementos relacionados con la adecuación y calidad de los contenidos textuales, iconos y controles de la interfaz.
A2: Código | B2: Criterio | C2: Valor | D2: Relevancia | E2: Comentarios | F2: Valor interno(vc) | G2: Valor interno de relevancia (rc) | H2: Factor de corrección (fc) | I2: Valor parcial | J2: Valor parcial 2
A3: EF.1 | B3: Se emplea un lenguaje claro y conciso | C3: 10 | D3: =IF(OR(TipoDeSitio="",C3="NA"),"",VLOOKUP(CONCATENATE(A3,": ",B3),Tabla626,MATCH(TipoDeSitio,Tipos,0)+1,0)) | E3: Párrafos cortos; etiquetas de campo directas: "Lugar de Origen", "Fecha del Traslado". | F3: =IF(C3="","",VLOOKUP(C3,ValoresVC,2,0)) | G3: =IF(D3="","",VLOOKUP($D3,ValoresRC,2,0)) | H3: =IF(OR(G3="",G3=0,'Cálculo de % usabilidad'!$F$5=0),"",G3/'Cálculo de % usabilidad'!$F$5) | I3: =IF(OR(H3="",F3=""),"",H3*F3) | J3: =IF(H3="","",H3*10)
A4: EF.2 | B4: Lenguaje amigable, familiar y cercano | C4: 10 | D4: =IF(OR(TipoDeSitio="",C4="NA"),"",VLOOKUP(CONCATENATE(A4,": ",B4),Tabla626,MATCH(TipoDeSitio,Tipos,0)+1,0)) | E4: Tono informativo y amable sin tecnicismos. | F4: =IF(C4="","",VLOOKUP(C4,ValoresVC,2,0)) | G4: =IF(D4="","",VLOOKUP($D4,ValoresRC,2,0)) | H4: =IF(OR(G4="",G4=0,'Cálculo de % usabilidad'!$F$5=0),"",G4/'Cálculo de % usabilidad'!$F$5) | I4: =IF(OR(H4="",F4=""),"",H4*F4) | J4: =IF(H4="","",H4*10)
A5: EF.3 | B5: Cada párrafo expresa una idea | C5: 10 | D5: =IF(OR(TipoDeSitio="",C5="NA"),"",VLOOKUP(CONCATENATE(A5,": ",B5),Tabla626,MATCH(TipoDeSitio,Tipos,0)+1,0)) | E5: Cada bloque de texto tiene un único propósito semántico. | F5: =IF(C5="","",VLOOKUP(C5,ValoresVC,2,0)) | G5: =IF(D5="","",VLOOKUP($D5,ValoresRC,2,0)) | H5: =IF(OR(G5="",G5=0,'Cálculo de % usabilidad'!$F$5=0),"",G5/'Cálculo de % usabilidad'!$F$5) | I5: =IF(OR(H5="",F5=""),"",H5*F5) | J5: =IF(H5="","",H5*10)
A6: EF.4 | B6: Uso consistente de los controles de la interfaz | C6: 10 | D6: =IF(OR(TipoDeSitio="",C6="NA"),"",VLOOKUP(CONCATENATE(A6,": ",B6),Tabla626,MATCH(TipoDeSitio,Tipos,0)+1,0)) | E6: Botones, selects e inputs siguen el patrón Bootstrap en todas las páginas. | F6: =IF(C6="","",VLOOKUP(C6,ValoresVC,2,0)) | G6: =IF(D6="","",VLOOKUP($D6,ValoresRC,2,0)) | H6: =IF(OR(G6="",G6=0,'Cálculo de % usabilidad'!$F$5=0),"",G6/'Cálculo de % usabilidad'!$F$5) | I6: =IF(OR(H6="",F6=""),"",H6*F6) | J6: =IF(H6="","",H6*10)
A7: EF.5 | B7: Metáforas visuales reconocibles y comprensibles por cualquier usuario (ej.: iconos) | C7: 10 | D7: =IF(OR(TipoDeSitio="",C7="NA"),"",VLOOKUP(CONCATENATE(A7,": ",B7),Tabla626,MATCH(TipoDeSitio,Tipos,0)+1,0)) | E7: Iconos de emoji (📍📞✉️) en la página de contacto; iconos de tema/idioma en la nav. | F7: =IF(C7="","",VLOOKUP(C7,ValoresVC,2,0)) | G7: =IF(D7="","",VLOOKUP($D7,ValoresRC,2,0)) | H7: =IF(OR(G7="",G7=0,'Cálculo de % usabilidad'!$F$5=0),"",G7/'Cálculo de % usabilidad'!$F$5) | I7: =IF(OR(H7="",F7=""),"",H7*F7) | J7: =IF(H7="","",H7*10)
A8: EF.6 | B8: Si se usan menús desplegables, orden coherente o alfabético | C8: 10 | D8: =IF(OR(TipoDeSitio="",C8="NA"),"",VLOOKUP(CONCATENATE(A8,": ",B8),Tabla626,MATCH(TipoDeSitio,Tipos,0)+1,0)) | E8: Lista de destinos en orden geográfico lógico; extras en orden lógico. | F8: =IF(C8="","",VLOOKUP(C8,ValoresVC,2,0)) | G8: =IF(D8="","",VLOOKUP($D8,ValoresRC,2,0)) | H8: =IF(OR(G8="",G8=0,'Cálculo de % usabilidad'!$F$5=0),"",G8/'Cálculo de % usabilidad'!$F$5) | I8: =IF(OR(H8="",F8=""),"",H8*F8) | J8: =IF(H8="","",H8*10)
A9: EF.7 | B9: Si el usuario tiene que rellenar un campo, las opciones disponibles se pueden seleccionar en vez de tener que escribirlas | C9: 10 | D9: =IF(OR(TipoDeSitio="",C9="NA"),"",VLOOKUP(CONCATENATE(A9,": ",B9),Tabla626,MATCH(TipoDeSitio,Tipos,0)+1,0)) | E9: Origen, destino, extras y número de pasajeros usan <select> e <input> estándar. | F9: =IF(C9="","",VLOOKUP(C9,ValoresVC,2,0)) | G9: =IF(D9="","",VLOOKUP($D9,ValoresRC,2,0)) | H9: =IF(OR(G9="",G9=0,'Cálculo de % usabilidad'!$F$5=0),"",G9/'Cálculo de % usabilidad'!$F$5) | I9: =IF(OR(H9="",F9=""),"",H9*F9) | J9: =IF(H9="","",H9*10) | K9: Núm.elementos evaluados | L9: =7-(COUNTIF(C3:C9,"NA")+COUNTBLANK(C3:C9)) | M9: (no contabiliza ni los vacíos ni los NA)
G10: =IF(SUM(G3:G9)=0,"",SUM(G3:G9))
A11: Instrucciones | C11: Leyenda Valor
A12: 1. Evalue cada criterio y rellene la columna "Valor" según la leyenda | C12: 0 | D12: No se cumple en absoluto | F12: NEP | G12: No se cumple en los enlaces principales
A13: 2. Añada sus comentarios o la referencia a los mismos en otro documento anexo en la columna "Comentarios" | C13: 10 | D13: Se cumple totalmente | F13: NPP | G13: No se cumple en la página principal
C14: NA | D14: Criterio no aplicable en el sitio | F14: NPI | G14: No se cumple en alguna página interior
C15: NTS | D15: No se cumple en todo el sitio | F15: S | G15: Se cumple el criterio

Sheet 7, Control y Retoalimentación
A1: CRITERIOS DEL "CONTROL Y RETORALIMENTACIÓN": Elementos relacionados con libertad del usuario en la navegación y la información proporcionada al mismo en el proceso de interacción con el sitio.
A2: Código | B2: Criterio | C2: Valor | D2: Relevancia | E2: Comentarios | F2: Valor interno(vc) | G2: Valor interno de relevancia (rc) | H2: Factor de corrección (fc) | I2: Valor parcial | J2: Valor parcial 2
A3: CR.1 | B3: El usuario tiene todo el control sobre la interfaz | C3: 10 | D3: =IF(OR(TipoDeSitio="",C3="NA"),"",VLOOKUP(CONCATENATE(A3,": ",B3),Tabla627,MATCH(TipoDeSitio,Tipos,0)+1,0)) | E3: El usuario puede navegar libremente, cancelar modales y modificar datos. | F3: =IF(C3="","",VLOOKUP(C3,ValoresVC,2,0)) | G3: =IF(D3="","",VLOOKUP($D3,ValoresRC,2,0)) | H3: =IF(OR(G3="",G3=0,'Cálculo de % usabilidad'!$F$5=0),"",G3/'Cálculo de % usabilidad'!$F$5) | I3: =IF(OR(H3="",F3=""),"",H3*F3) | J3: =IF(H3="","",H3*10)
A4: CR.2 | B4: Se informa al usuario acerca de lo que está pasando | C4: 10 | D4: =IF(OR(TipoDeSitio="",C4="NA"),"",VLOOKUP(CONCATENATE(A4,": ",B4),Tabla627,MATCH(TipoDeSitio,Tipos,0)+1,0)) | E4: Modal de confirmación muestra resumen antes de pagar; precio se actualiza en tiempo real. | F4: =IF(C4="","",VLOOKUP(C4,ValoresVC,2,0)) | G4: =IF(D4="","",VLOOKUP($D4,ValoresRC,2,0)) | H4: =IF(OR(G4="",G4=0,'Cálculo de % usabilidad'!$F$5=0),"",G4/'Cálculo de % usabilidad'!$F$5) | I4: =IF(OR(H4="",F4=""),"",H4*F4) | J4: =IF(H4="","",H4*10)
A5: CR.3 | B5: Se informa al usuario de lo que ha pasado | C5: 10 | D5: =IF(OR(TipoDeSitio="",C5="NA"),"",VLOOKUP(CONCATENATE(A5,": ",B5),Tabla627,MATCH(TipoDeSitio,Tipos,0)+1,0)) | E5: Código de reserva TX-12345 generado y mostrado al finalizar el pago. | F5: =IF(C5="","",VLOOKUP(C5,ValoresVC,2,0)) | G5: =IF(D5="","",VLOOKUP($D5,ValoresRC,2,0)) | H5: =IF(OR(G5="",G5=0,'Cálculo de % usabilidad'!$F$5=0),"",G5/'Cálculo de % usabilidad'!$F$5) | I5: =IF(OR(H5="",F5=""),"",H5*F5) | J5: =IF(H5="","",H5*10)
A6: CR.4 | B6: Existen sistemas de validación antes de que el usuario envíe información para tratar de evitar errores | C6: 10 | D6: =IF(OR(TipoDeSitio="",C6="NA"),"",VLOOKUP(CONCATENATE(A6,": ",B6),Tabla627,MATCH(TipoDeSitio,Tipos,0)+1,0)) | E6: bookingValidation.js valida todos los campos antes de mostrar el modal de confirmación. | F6: =IF(C6="","",VLOOKUP(C6,ValoresVC,2,0)) | G6: =IF(D6="","",VLOOKUP($D6,ValoresRC,2,0)) | H6: =IF(OR(G6="",G6=0,'Cálculo de % usabilidad'!$F$5=0),"",G6/'Cálculo de % usabilidad'!$F$5) | I6: =IF(OR(H6="",F6=""),"",H6*F6) | J6: =IF(H6="","",H6*10)
A7: CR.5 | B7: Cuando se produce un error, se informa de forma clara y no alarmista al usuario de lo ocurrido y de cómo solucionar el problema | C7: 10 | D7: =IF(OR(TipoDeSitio="",C7="NA"),"",VLOOKUP(CONCATENATE(A7,": ",B7),Tabla627,MATCH(TipoDeSitio,Tipos,0)+1,0)) | E7: Mensajes de error inline junto a cada campo inválido. | F7: =IF(C7="","",VLOOKUP(C7,ValoresVC,2,0)) | G7: =IF(D7="","",VLOOKUP($D7,ValoresRC,2,0)) | H7: =IF(OR(G7="",G7=0,'Cálculo de % usabilidad'!$F$5=0),"",G7/'Cálculo de % usabilidad'!$F$5) | I7: =IF(OR(H7="",F7=""),"",H7*F7) | J7: =IF(H7="","",H7*10)
A8: CR.6 | B8: Se ha controlado el tiempo de respuesta | C8: 10 | D8: =IF(OR(TipoDeSitio="",C8="NA"),"",VLOOKUP(CONCATENATE(A8,": ",B8),Tabla627,MATCH(TipoDeSitio,Tipos,0)+1,0)) | E8: Todo el procesamiento es en cliente; sin latencia de red. | F8: =IF(C8="","",VLOOKUP(C8,ValoresVC,2,0)) | G8: =IF(D8="","",VLOOKUP($D8,ValoresRC,2,0)) | H8: =IF(OR(G8="",G8=0,'Cálculo de % usabilidad'!$F$5=0),"",G8/'Cálculo de % usabilidad'!$F$5) | I8: =IF(OR(H8="",F8=""),"",H8*F8) | J8: =IF(H8="","",H8*10)
A9: CR.7 | B9: Se ha evitado que las ventanas del sitio anulen o se superpongan a la del navegador | C9: 10 | D9: =IF(OR(TipoDeSitio="",C9="NA"),"",VLOOKUP(CONCATENATE(A9,": ",B9),Tabla627,MATCH(TipoDeSitio,Tipos,0)+1,0)) | E9: Los modales Bootstrap no abren ventanas nuevas; se superponen en la misma pestaña. | F9: =IF(C9="","",VLOOKUP(C9,ValoresVC,2,0)) | G9: =IF(D9="","",VLOOKUP($D9,ValoresRC,2,0)) | H9: =IF(OR(G9="",G9=0,'Cálculo de % usabilidad'!$F$5=0),"",G9/'Cálculo de % usabilidad'!$F$5) | I9: =IF(OR(H9="",F9=""),"",H9*F9) | J9: =IF(H9="","",H9*10)
A10: CR.8 | B10: Se ha evitado la proliferación de ventanas en la pantalla del usuario | C10: 10 | D10: =IF(OR(TipoDeSitio="",C10="NA"),"",VLOOKUP(CONCATENATE(A10,": ",B10),Tabla627,MATCH(TipoDeSitio,Tipos,0)+1,0)) | E10: Máximo un modal visible a la vez (confirmación o pago). | F10: =IF(C10="","",VLOOKUP(C10,ValoresVC,2,0)) | G10: =IF(D10="","",VLOOKUP($D10,ValoresRC,2,0)) | H10: =IF(OR(G10="",G10=0,'Cálculo de % usabilidad'!$F$5=0),"",G10/'Cálculo de % usabilidad'!$F$5) | I10: =IF(OR(H10="",F10=""),"",H10*F10) | J10: =IF(H10="","",H10*10)
A11: CR.9 | B11: Se ha evitado la descarga por parte del usuario de plugins adicionales | C11: 10 | D11: =IF(OR(TipoDeSitio="",C11="NA"),"",VLOOKUP(CONCATENATE(A11,": ",B11),Tabla627,MATCH(TipoDeSitio,Tipos,0)+1,0)) | E11: Solo se requiere Bootstrap CDN; no hay plugins propietarios. | F11: =IF(C11="","",VLOOKUP(C11,ValoresVC,2,0)) | G11: =IF(D11="","",VLOOKUP($D11,ValoresRC,2,0)) | H11: =IF(OR(G11="",G11=0,'Cálculo de % usabilidad'!$F$5=0),"",G11/'Cálculo de % usabilidad'!$F$5) | I11: =IF(OR(H11="",F11=""),"",H11*F11) | J11: =IF(H11="","",H11*10)
A12: CR.10 | B12: Si existen tareas de varios pasos, se indica al usuario en cual está y cuantos faltan para completar la tarea | C12: 7 | D12: =IF(OR(TipoDeSitio="",C12="NA"),"",VLOOKUP(CONCATENATE(A12,": ",B12),Tabla627,MATCH(TipoDeSitio,Tipos,0)+1,0)) | E12: Los modales indican la fase (Confirmar / Pagar) pero no muestran "Paso X de Y". | F12: =IF(C12="","",VLOOKUP(C12,ValoresVC,2,0)) | G12: =IF(D12="","",VLOOKUP($D12,ValoresRC,2,0)) | H12: =IF(OR(G12="",G12=0,'Cálculo de % usabilidad'!$F$5=0),"",G12/'Cálculo de % usabilidad'!$F$5) | I12: =IF(OR(H12="",F12=""),"",H12*F12) | J12: =IF(H12="","",H12*10) | K12: Núm.elementos evaluados | L12: =10-(COUNTIF(C3:C12,"NA")+COUNTBLANK(C3:C12)) | M12: (no contabiliza ni los vacíos ni los NA)
G13: =IF(SUM(G3:G12)=0,"",SUM(G3:G12))
A14: Instrucciones | C14: Leyenda Valor
A15: 1. Evalue cada criterio y rellene la columna "Valor" según la leyenda | C15: 0 | D15: No se cumple en absoluto | F15: NEP | G15: No se cumple en los enlaces principales
A16: 2. Añada sus comentarios o la referencia a los mismos en otro documento anexo en la columna "Comentarios" | C16: 10 | D16: Se cumple totalmente | F16: NPP | G16: No se cumple en la página principal
C17: NA | D17: Criterio no aplicable en el sitio | F17: NPI | G17: No se cumple en alguna página interior
C18: NTS | D18: No se cumple en todo el sitio | F18: S | G18: Se cumple el criterio

Sheet 8, Elementos multimedia
A1: CRITERIOS DEL "ELEMENTOS MULTIMEDIA": Elementos relacionados con el grado de adecuación de los contenidos multimedia al sitio web.
A2: Código | B2: Criterio | C2: Valor | D2: Relevancia | E2: Comentarios | F2: Valor interno(vc) | G2: Valor interno de relevancia (rc) | H2: Factor de corrección (fc) | I2: Valor parcial | J2: Valor parcial 2
A3: EM.1 | B3: Fotografías bien recortadas | C3: NA | D3: =IF(OR(TipoDeSitio="",C3="NA"),"",VLOOKUP(CONCATENATE(A3,": ",B3),Tabla628,MATCH(TipoDeSitio,Tipos,0)+1,0)) | E3: El prototipo no incluye fotografías. | F3: =IF(C3="","",VLOOKUP(C3,ValoresVC,2,0)) | G3: =IF(D3="","",VLOOKUP($D3,ValoresRC,2,0)) | H3: =IF(OR(G3="",G3=0,'Cálculo de % usabilidad'!$F$5=0),"",G3/'Cálculo de % usabilidad'!$F$5) | I3: =IF(OR(H3="",F3=""),"",H3*F3) | J3: =IF(H3="","",H3*10)
A4: EM.2 | B4: Fotografías comprensibles | C4: NA | D4: =IF(OR(TipoDeSitio="",C4="NA"),"",VLOOKUP(CONCATENATE(A4,": ",B4),Tabla628,MATCH(TipoDeSitio,Tipos,0)+1,0)) | E4: El prototipo no incluye fotografías. | F4: =IF(C4="","",VLOOKUP(C4,ValoresVC,2,0)) | G4: =IF(D4="","",VLOOKUP($D4,ValoresRC,2,0)) | H4: =IF(OR(G4="",G4=0,'Cálculo de % usabilidad'!$F$5=0),"",G4/'Cálculo de % usabilidad'!$F$5) | I4: =IF(OR(H4="",F4=""),"",H4*F4) | J4: =IF(H4="","",H4*10)
A5: EM.3 | B5: Fotografías con correcta resolución | C5: NA | D5: =IF(OR(TipoDeSitio="",C5="NA"),"",VLOOKUP(CONCATENATE(A5,": ",B5),Tabla628,MATCH(TipoDeSitio,Tipos,0)+1,0)) | E5: El prototipo no incluye fotografías. | F5: =IF(C5="","",VLOOKUP(C5,ValoresVC,2,0)) | G5: =IF(D5="","",VLOOKUP($D5,ValoresRC,2,0)) | H5: =IF(OR(G5="",G5=0,'Cálculo de % usabilidad'!$F$5=0),"",G5/'Cálculo de % usabilidad'!$F$5) | I5: =IF(OR(H5="",F5=""),"",H5*F5) | J5: =IF(H5="","",H5*10)
A6: EM.4 | B6: El uso de imágenes o animaciones proporciona algún tipo de valor añadido | C6: 8 | D6: =IF(OR(TipoDeSitio="",C6="NA"),"",VLOOKUP(CONCATENATE(A6,": ",B6),Tabla628,MATCH(TipoDeSitio,Tipos,0)+1,0)) | E6: El logo SVG de taxi refuerza la identidad visual del servicio. | F6: =IF(C6="","",VLOOKUP(C6,ValoresVC,2,0)) | G6: =IF(D6="","",VLOOKUP($D6,ValoresRC,2,0)) | H6: =IF(OR(G6="",G6=0,'Cálculo de % usabilidad'!$F$5=0),"",G6/'Cálculo de % usabilidad'!$F$5) | I6: =IF(OR(H6="",F6=""),"",H6*F6) | J6: =IF(H6="","",H6*10)
A7: EM.5 | B7: Se ha evitado el uso de animaciones cíclicas | C7: 10 | D7: =IF(OR(TipoDeSitio="",C7="NA"),"",VLOOKUP(CONCATENATE(A7,": ",B7),Tabla628,MATCH(TipoDeSitio,Tipos,0)+1,0)) | E7: No se usan animaciones GIF ni CSS en bucle. | F7: =IF(C7="","",VLOOKUP(C7,ValoresVC,2,0)) | G7: =IF(D7="","",VLOOKUP($D7,ValoresRC,2,0)) | H7: =IF(OR(G7="",G7=0,'Cálculo de % usabilidad'!$F$5=0),"",G7/'Cálculo de % usabilidad'!$F$5) | I7: =IF(OR(H7="",F7=""),"",H7*F7) | J7: =IF(H7="","",H7*10)
A8: EM.6 | B8: El uso de sonido proporciona algún tipo de valor añadido | C8: NA | D8: =IF(OR(TipoDeSitio="",C8="NA"),"",VLOOKUP(CONCATENATE(A8,": ",B8),Tabla628,MATCH(TipoDeSitio,Tipos,0)+1,0)) | E8: El prototipo no incluye audio. | F8: =IF(C8="","",VLOOKUP(C8,ValoresVC,2,0)) | G8: =IF(D8="","",VLOOKUP($D8,ValoresRC,2,0)) | H8: =IF(OR(G8="",G8=0,'Cálculo de % usabilidad'!$F$5=0),"",G8/'Cálculo de % usabilidad'!$F$5) | I8: =IF(OR(H8="",F8=""),"",H8*F8) | J8: =IF(H8="","",H8*10) | K8: Núm.elementos evaluados | L8: =6-(COUNTIF(C3:C8,"NA")+COUNTBLANK(C3:C8)) | M8: (no contabiliza ni los vacíos ni los NA)
G9: =IF(SUM(G3:G8)=0,"",SUM(G3:G8))
A10: Instrucciones | C10: Leyenda Valor
A11: 1. Evalue cada criterio y rellene la columna "Valor" según la leyenda | C11: 0 | D11: No se cumple en absoluto | F11: NEP | G11: No se cumple en los enlaces principales
A12: 2. Añada sus comentarios o la referencia a los mismos en otro documento anexo en la columna "Comentarios" | C12: 10 | D12: Se cumple totalmente | F12: NPP | G12: No se cumple en la página principal
C13: NA | D13: Criterio no aplicable en el sitio | F13: NPI | G13: No se cumple en alguna página interior
C14: NTS | D14: No se cumple en todo el sitio | F14: S | G14: Se cumple el criterio

Sheet 9, Búsqueda
A1: CRITERIOS DEL "BÚSQUEDA": Elementos relacionados con el buscador implementado en el sitio web.
A2: Código | B2: Criterio | C2: Valor | D2: Relevancia | E2: Comentarios | F2: Valor interno(vc) | G2: Valor interno de relevancia (rc) | H2: Factor de corrección (fc) | I2: Valor parcial | J2: Valor parcial 2
A3: BU.1 | B3: La búsqueda, si es necesaria, se encuentra accesible desde todas las páginas del sitio | C3: NA | D3: =IF(OR(TipoDeSitio="",C3="NA"),"",VLOOKUP(CONCATENATE(A3,": ",B3),Tabla629,MATCH(TipoDeSitio,Tipos,0)+1,0)) | E3: No se implementa buscador global; la localización de reservas es un flujo específico. | F3: =IF(C3="","",VLOOKUP(C3,ValoresVC,2,0)) | G3: =IF(D3="","",VLOOKUP($D3,ValoresRC,2,0)) | H3: =IF(OR(G3="",G3=0,'Cálculo de % usabilidad'!$F$5=0),"",G3/'Cálculo de % usabilidad'!$F$5) | I3: =IF(OR(H3="",F3=""),"",H3*F3) | J3: =IF(H3="","",H3*10)
A4: BU.2 | B4: Es fácilmente reconocible como tal | C4: NA | D4: =IF(OR(TipoDeSitio="",C4="NA"),"",VLOOKUP(CONCATENATE(A4,": ",B4),Tabla629,MATCH(TipoDeSitio,Tipos,0)+1,0)) | E4: No aplica. | F4: =IF(C4="","",VLOOKUP(C4,ValoresVC,2,0)) | G4: =IF(D4="","",VLOOKUP($D4,ValoresRC,2,0)) | H4: =IF(OR(G4="",G4=0,'Cálculo de % usabilidad'!$F$5=0),"",G4/'Cálculo de % usabilidad'!$F$5) | I4: =IF(OR(H4="",F4=""),"",H4*F4) | J4: =IF(H4="","",H4*10)
A5: BU.3 | B5: Se encuentra fácilmente accesible | C5: NA | D5: =IF(OR(TipoDeSitio="",C5="NA"),"",VLOOKUP(CONCATENATE(A5,": ",B5),Tabla629,MATCH(TipoDeSitio,Tipos,0)+1,0)) | E5: No aplica. | F5: =IF(C5="","",VLOOKUP(C5,ValoresVC,2,0)) | G5: =IF(D5="","",VLOOKUP($D5,ValoresRC,2,0)) | H5: =IF(OR(G5="",G5=0,'Cálculo de % usabilidad'!$F$5=0),"",G5/'Cálculo de % usabilidad'!$F$5) | I5: =IF(OR(H5="",F5=""),"",H5*F5) | J5: =IF(H5="","",H5*10)
A6: BU.4 | B6: La caja de texto es lo suficientemente ancha | C6: NA | D6: =IF(OR(TipoDeSitio="",C6="NA"),"",VLOOKUP(CONCATENATE(A6,": ",B6),Tabla629,MATCH(TipoDeSitio,Tipos,0)+1,0)) | E6: No aplica. | F6: =IF(C6="","",VLOOKUP(C6,ValoresVC,2,0)) | G6: =IF(D6="","",VLOOKUP($D6,ValoresRC,2,0)) | H6: =IF(OR(G6="",G6=0,'Cálculo de % usabilidad'!$F$5=0),"",G6/'Cálculo de % usabilidad'!$F$5) | I6: =IF(OR(H6="",F6=""),"",H6*F6) | J6: =IF(H6="","",H6*10)
A7: BU.5 | B7: Sistema de búsqueda simple y claro | C7: NA | D7: =IF(OR(TipoDeSitio="",C7="NA"),"",VLOOKUP(CONCATENATE(A7,": ",B7),Tabla629,MATCH(TipoDeSitio,Tipos,0)+1,0)) | E7: No aplica. | F7: =IF(C7="","",VLOOKUP(C7,ValoresVC,2,0)) | G7: =IF(D7="","",VLOOKUP($D7,ValoresRC,2,0)) | H7: =IF(OR(G7="",G7=0,'Cálculo de % usabilidad'!$F$5=0),"",G7/'Cálculo de % usabilidad'!$F$5) | I7: =IF(OR(H7="",F7=""),"",H7*F7) | J7: =IF(H7="","",H7*10)
A8: BU.6 | B8: Permite la búsqueda avanzada | C8: NA | D8: =IF(OR(TipoDeSitio="",C8="NA"),"",VLOOKUP(CONCATENATE(A8,": ",B8),Tabla629,MATCH(TipoDeSitio,Tipos,0)+1,0)) | E8: No aplica. | F8: =IF(C8="","",VLOOKUP(C8,ValoresVC,2,0)) | G8: =IF(D8="","",VLOOKUP($D8,ValoresRC,2,0)) | H8: =IF(OR(G8="",G8=0,'Cálculo de % usabilidad'!$F$5=0),"",G8/'Cálculo de % usabilidad'!$F$5) | I8: =IF(OR(H8="",F8=""),"",H8*F8) | J8: =IF(H8="","",H8*10)
A9: BU.7 | B9: Muestra los resultados de la búsqueda de forma comprensible para el usuario | C9: NA | D9: =IF(OR(TipoDeSitio="",C9="NA"),"",VLOOKUP(CONCATENATE(A9,": ",B9),Tabla629,MATCH(TipoDeSitio,Tipos,0)+1,0)) | E9: No aplica. | F9: =IF(C9="","",VLOOKUP(C9,ValoresVC,2,0)) | G9: =IF(D9="","",VLOOKUP($D9,ValoresRC,2,0)) | H9: =IF(OR(G9="",G9=0,'Cálculo de % usabilidad'!$F$5=0),"",G9/'Cálculo de % usabilidad'!$F$5) | I9: =IF(OR(H9="",F9=""),"",H9*F9) | J9: =IF(H9="","",H9*10)
A10: BU.8 | B10: Asiste al usuario en caso de no poder ofrecer resultados para una consulta dada | C10: NA | D10: =IF(OR(TipoDeSitio="",C10="NA"),"",VLOOKUP(CONCATENATE(A10,": ",B10),Tabla629,MATCH(TipoDeSitio,Tipos,0)+1,0)) | E10: No aplica. | F10: =IF(C10="","",VLOOKUP(C10,ValoresVC,2,0)) | G10: =IF(D10="","",VLOOKUP($D10,ValoresRC,2,0)) | H10: =IF(OR(G10="",G10=0,'Cálculo de % usabilidad'!$F$5=0),"",G10/'Cálculo de % usabilidad'!$F$5) | I10: =IF(OR(H10="",F10=""),"",H10*F10) | J10: =IF(H10="","",H10*10) | K10: Núm.elementos evaluados | L10: =8-(COUNTIF(C3:C10,"NA")+COUNTBLANK(C3:C10)) | M10: (no contabiliza ni los vacíos ni los NA)
G11: =IF(SUM(G3:G10)=0,"",SUM(G3:G10))
A12: Instrucciones | C12: Leyenda Valor
A13: 1. Evalue cada criterio y rellene la columna "Valor" según la leyenda | C13: 0 | D13: No se cumple en absoluto | F13: NEP | G13: No se cumple en los enlaces principales
A14: 2. Añada sus comentarios o la referencia a los mismos en otro documento anexo en la columna "Comentarios" | C14: 10 | D14: Se cumple totalmente | F14: NPP | G14: No se cumple en la página principal
C15: NA | D15: Criterio no aplicable en el sitio | F15: NPI | G15: No se cumple en alguna página interior
C16: NTS | D16: No se cumple en todo el sitio | F16: S | G16: Se cumple el criterio

Sheet 10, Ayuda
A1: CRITERIOS DEL "AYUDA": Elementos relacionados con la ayuda ofrecida al usuario durante la navegación por el sitio.
A2: Código | B2: Criterio | C2: Valor | D2: Relevancia | E2: Comentarios | F2: Valor interno(vc) | G2: Valor interno de relevancia (rc) | H2: Factor de corrección (fc) | I2: Valor parcial | J2: Valor parcial 2
A3: AY.1 | B3: El enlace a la sección de Ayuda está colocado en una zona visible y estándar | C3: 0 | D3: =IF(OR(TipoDeSitio="",C3="NA"),"",VLOOKUP(CONCATENATE(A3,": ",B3),Tabla630,MATCH(TipoDeSitio,Tipos,0)+1,0)) | E3: No existe página ni enlace de Ayuda en el sitio. | F3: =IF(C3="","",VLOOKUP(C3,ValoresVC,2,0)) | G3: =IF(D3="","",VLOOKUP($D3,ValoresRC,2,0)) | H3: =IF(OR(G3="",G3=0,'Cálculo de % usabilidad'!$F$5=0),"",G3/'Cálculo de % usabilidad'!$F$5) | I3: =IF(OR(H3="",F3=""),"",H3*F3) | J3: =IF(H3="","",H3*10)
A4: AY.2 | B4: Fácil acceso y retorno al/del sistema de ayuda | C4: 0 | D4: =IF(OR(TipoDeSitio="",C4="NA"),"",VLOOKUP(CONCATENATE(A4,": ",B4),Tabla630,MATCH(TipoDeSitio,Tipos,0)+1,0)) | E4: No existe sistema de ayuda al que acceder o del que volver. | F4: =IF(C4="","",VLOOKUP(C4,ValoresVC,2,0)) | G4: =IF(D4="","",VLOOKUP($D4,ValoresRC,2,0)) | H4: =IF(OR(G4="",G4=0,'Cálculo de % usabilidad'!$F$5=0),"",G4/'Cálculo de % usabilidad'!$F$5) | I4: =IF(OR(H4="",F4=""),"",H4*F4) | J4: =IF(H4="","",H4*10)
A5: AY.3 | B5: Se ofrece ayuda contextual en tareas complejas | C5: 7 | D5: =IF(OR(TipoDeSitio="",C5="NA"),"",VLOOKUP(CONCATENATE(A5,": ",B5),Tabla630,MATCH(TipoDeSitio,Tipos,0)+1,0)) | E5: Los campos del formulario incluyen textos de ayuda (form-text Bootstrap) como "Selecciona un destino disponible de Tenerife" e indicaciones de hora y fecha. | F5: =IF(C5="","",VLOOKUP(C5,ValoresVC,2,0)) | G5: =IF(D5="","",VLOOKUP($D5,ValoresRC,2,0)) | H5: =IF(OR(G5="",G5=0,'Cálculo de % usabilidad'!$F$5=0),"",G5/'Cálculo de % usabilidad'!$F$5) | I5: =IF(OR(H5="",F5=""),"",H5*F5) | J5: =IF(H5="","",H5*10)
A6: AY.4 | B6: FAQs (si las hay) correcta la elección como la redacción de las preguntas | C6: NA | D6: =IF(OR(TipoDeSitio="",C6="NA"),"",VLOOKUP(CONCATENATE(A6,": ",B6),Tabla630,MATCH(TipoDeSitio,Tipos,0)+1,0)) | E6: No hay sección de preguntas frecuentes. | F6: =IF(C6="","",VLOOKUP(C6,ValoresVC,2,0)) | G6: =IF(D6="","",VLOOKUP($D6,ValoresRC,2,0)) | H6: =IF(OR(G6="",G6=0,'Cálculo de % usabilidad'!$F$5=0),"",G6/'Cálculo de % usabilidad'!$F$5) | I6: =IF(OR(H6="",F6=""),"",H6*F6) | J6: =IF(H6="","",H6*10)
A7: AY.5 | B7: FAQs (si las hay) correcta la redacción de las respuestas | C7: NA | D7: =IF(OR(TipoDeSitio="",C7="NA"),"",VLOOKUP(CONCATENATE(A7,": ",B7),Tabla630,MATCH(TipoDeSitio,Tipos,0)+1,0)) | E7: No hay sección de preguntas frecuentes. | F7: =IF(C7="","",VLOOKUP(C7,ValoresVC,2,0)) | G7: =IF(D7="","",VLOOKUP($D7,ValoresRC,2,0)) | H7: =IF(OR(G7="",G7=0,'Cálculo de % usabilidad'!$F$5=0),"",G7/'Cálculo de % usabilidad'!$F$5) | I7: =IF(OR(H7="",F7=""),"",H7*F7) | J7: =IF(H7="","",H7*10) | K7: Núm.elementos evaluados | L7: =5-(COUNTIF(C3:C7,"NA")+COUNTBLANK(C3:C7)) | M7: (no contabiliza ni los vacíos ni los NA)
G8: =IF(SUM(G3:G7)=0,"",SUM(G3:G7))
A9: Instrucciones | C9: Leyenda Valor
A10: 1. Evalue cada criterio y rellene la columna "Valor" según la leyenda | C10: 0 | D10: No se cumple en absoluto | F10: NEP | G10: No se cumple en los enlaces principales
A11: 2. Añada sus comentarios o la referencia a los mismos en otro documento anexo en la columna "Comentarios" | C11: 10 | D11: Se cumple totalmente | F11: NPP | G11: No se cumple en la página principal
C12: NA | D12: Criterio no aplicable en el sitio | F12: NPI | G12: No se cumple en alguna página interior
C13: NTS | D13: No se cumple en todo el sitio | F13: S | G13: Se cumple el criterio

Sheet Cálculo de % usabilidad
A2: CÁLCULO DEL PORCENTAJE DE USABILIDAD
D3: Datos para el cálculo:
A4: Porcentaje de usabilidad* | B4: =IF(OR(ISERROR(F6),ISERROR(F7),F6="",F7="",F6=0,F7=0),"",(F6/F7)*100) | D4: Nº de criterios evaluados | F4: =SUM('1, Aspectos generales'!L12,'2, Identidad e Información'!L9,'3, Estructura y navegación'!L16,'4, Rotulado'!L8,'5, Layout de la página'!L12,'6, Entendibilidad y Facilidad'!L9,'7, Control y Retoalimentación'!L12,'8, Elementos multimedia'!L8,'9, Búsqueda'!L10,'10, Ayuda'!L7)
D5: El sumatorio de los valores de relevancia de los criterios evaluados es: | F5: =SUM('1, Aspectos generales'!G13,'2, Identidad e Información'!G10,'3, Estructura y navegación'!G17,'4, Rotulado'!G9,'5, Layout de la página'!G13,'6, Entendibilidad y Facilidad'!G10,'7, Control y Retoalimentación'!G13,'8, Elementos multimedia'!G9,'9, Búsqueda'!G11,'10, Ayuda'!G8) | G5: *A los NA no se les aplica relevancia
D6: Sumatorio de la columna i de cada criterio | F6: =SUM('1, Aspectos generales'!I3:I12,'2, Identidad e Información'!I3:I9,'3, Estructura y navegación'!I3:I16,'4, Rotulado'!I3:I8,'5, Layout de la página'!I3:I12,'6, Entendibilidad y Facilidad'!I3:I9,'7, Control y Retoalimentación'!I3:I12,'8, Elementos multimedia'!I3:I8,'9, Búsqueda'!I3:I10,'10, Ayuda'!I3:I7) | G6: *Los NA no se tienen en cuenta
D7: Sumatorio de la columna h *10 de cada criterio | F7: =SUM('1, Aspectos generales'!J3:J12,'2, Identidad e Información'!J3:J9,'3, Estructura y navegación'!J3:J16,'4, Rotulado'!J3:J8,'5, Layout de la página'!J3:J12,'7, Control y Retoalimentación'!J3:J12,'8, Elementos multimedia'!J3:J8,'6, Entendibilidad y Facilidad'!J3:J9,'9, Búsqueda'!J3:J10,'10, Ayuda'!J3:J7) | G7: *Los NA no se tienen en cuenta
A8: Se obtiene de aplicar la siguiente fórmula:
B11: nce: número de criterios evaluados. Será como máximo los 83. Los NA no contabilizan. Se toma de la celda E14 de esta hoja (NumEval)
B12: vc: valor de evaluación de un criterio (campo de la columna f "Valor interno" de cada criterio en cada hoja)
B13: fc: Factor de corrección aplicado al criterio evaluado.
B14: El valor del factor de corrección de cada uno de los criterios evaluados se obtiene de la siguiente manera:
D17: rc : Valor de relevancia que corresponde a un criterio (campo de la columna g "Valor interno de Relevancia")

Sheet Tablas de relevancia
A1: TABLA 6.21. RELEVANCIA DEL INCUMPLIMIENTO DE LOS CRITERIOS DE "ASPECTOS GENERALES"
B2: Tipo de Sitio
A3: Criterio | B3: Administración Pública / Institucional | C3: Banca electrónica | D3: Blog | E3: Comercio electrónico | F3: Comunicación / Noticias | G3: Corporativo / Empresa | H3: Descargas | I3: Educativo / Formativo | J3: Entornos colaborativos / Wikis | K3: Foros / Chat | L3: Ocio / Entretenimiento | M3: Personal | N3: Portal de Servicios | O3: Servicios interactivos basados en imágenes | P3: Servicios interactivos no basados en imágenes | Q3: Webmail / Correo
A4: =CONCATENATE('1, Aspectos generales'!A3,": ",'1, Aspectos generales'!B3) | B4: MA | C4: MA | D4: MO | E4: MA | F4: ME | G4: MA | H4: ME | I4: MA | J4: MA | K4: MO | L4: ME | M4: ME | N4: MA | O4: MA | P4: MA | Q4: ME
A5: =CONCATENATE('1, Aspectos generales'!A4,": ",'1, Aspectos generales'!B4) | B5: CR | C5: CR | D5: MO | E5: CR | F5: CR | G5: MA | H5: MA | I5: CR | J5: MA | K5: MO | L5: ME | M5: ME | N5: MA | O5: MA | P5: MA | Q5: MA
A6: =CONCATENATE('1, Aspectos generales'!A5,": ",'1, Aspectos generales'!B5) | B6: MA | C6: MA | D6: ME | E6: MA | F6: MA | G6: MA | H6: MA | I6: MA | J6: MA | K6: MA | L6: ME | M6: ME | N6: MA | O6: ME | P6: MA | Q6: MA
A7: =CONCATENATE('1, Aspectos generales'!A6,": ",'1, Aspectos generales'!B6) | B7: MA | C7: MA | D7: MO | E7: ME | F7: MA | G7: ME | H7: MO | I7: ME | J7: ME | K7: ME | L7: ME | M7: ME | N7: ME | O7: ME | P7: ME | Q7: MA
A8: =CONCATENATE('1, Aspectos generales'!A7,": ",'1, Aspectos generales'!B7) | B8: MA | C8: MA | D8: ME | E8: MA | F8: ME | G8: ME | H8: ME | I8: ME | J8: ME | K8: ME | L8: ME | M8: ME | N8: MA | O8: MO | P8: ME | Q8: MA
A9: =CONCATENATE('1, Aspectos generales'!A8,": ",'1, Aspectos generales'!B8) | B9: CR | C9: MA | D9: ME | E9: MA | F9: MA | G9: ME | H9: ME | I9: MA | J9: ME | K9: ME | L9: ME | M9: ME | N9: MA | O9: MA | P9: ME | Q9: MA
A10: =CONCATENATE('1, Aspectos generales'!A9,": ",'1, Aspectos generales'!B9) | B10: MA | C10: MA | D10: MA | E10: MA | F10: MA | G10: MA | H10: MO | I10: MA | J10: MA | K10: MA | L10: ME | M10: MO | N10: MA | O10: ME | P10: ME | Q10: ME
A11: =CONCATENATE('1, Aspectos generales'!A10,": ",'1, Aspectos generales'!B10) | B11: MA | C11: MA | D11: MO | E11: MA | F11: MA | G11: MA | H11: MO | I11: ME | J11: MO | K11: MO | L11: MO | M11: MO | N11: ME | O11: MO | P11: ME | Q11: ME
A12: =CONCATENATE('1, Aspectos generales'!A11,": ",'1, Aspectos generales'!B11) | B12: MA | C12: MA | D12: ME | E12: MA | F12: MA | G12: ME | H12: MO | I12: ME | J12: ME | K12: ME | L12: MO | M12: ME | N12: ME | O12: MO | P12: ME | Q12: ME
A13: =CONCATENATE('1, Aspectos generales'!A12,": ",'1, Aspectos generales'!B12) | B13: MA | C13: ME | D13: CR | E13: MA | F13: CR | G13: ME | H13: MA | I13: ME | J13: MA | K13: MA | L13: MA | M13: ME | N13: MA | O13: MA | P13: MA | Q13: CR
A15: TABLA 6.22. RELEVANCIA DEL INCUMPLIMIENTO DE LOS CRITERIOS DE "IDENTIDAD E INFORMACIÓN"
B16: Tipo de Sitio
A17: Criterio | B17: =B$3 | C17: =C$3 | D17: =D$3 | E17: =E$3 | F17: =F$3 | G17: =G$3 | H17: =H$3 | I17: =I$3 | ... Q17: =Q$3
A18: =CONCATENATE('2, Identidad e Información'!A3,": ",'2, Identidad e Información'!B3) | B18: MA | C18: ME | D18: MO | E18: ME | F18: ME | G18: ME | H18: ME | I18: MO | J18: MO | K18: MO | L18: MO | M18: MO | N18: ME | O18: MO | P18: MO | Q18: ME
A19: =CONCATENATE('2, Identidad e Información'!A4,": ",'2, Identidad e Información'!B4) | B19: MA | C19: MA | D19: ME | E19: MA | F19: ME | G19: MA | H19: MO | I19: ME | J19: ME | K19: ME | L19: MO | M19: MO | N19: ME | O19: ME | P19: ME | Q19: ME
A20: =CONCATENATE('2, Identidad e Información'!A5,": ",'2, Identidad e Información'!B5) | B20: ME | C20: ME | D20: MO | E20: ME | F20: MO | G20: ME | H20: MO | I20: ME | J20: MO | K20: MO | L20: MO | M20: ME | N20: ME | O20: MO | P20: ME | Q20: MO
A21: =CONCATENATE('2, Identidad e Información'!A6,": ",'2, Identidad e Información'!B6) | B21: MA | C21: MA | D21: ME | E21: ME | F21: ME | G21: ME | H21: ME | I21: ME | J21: ME | K21: ME | L21: ME | M21: MO | N21: ME | O21: MO | P21: ME | Q21: ME
A22: =CONCATENATE('2, Identidad e Información'!A7,": ",'2, Identidad e Información'!B7) | B22: MA | C22: MA | D22: ME | E22: MA | F22: ME | G22: MA | H22: MO | I22: ME | J22: ME | K22: ME | L22: MO | M22: ME | N22: ME | O22: ME | P22: ME | Q22: MO
A23: =CONCATENATE('2, Identidad e Información'!A8,": ",'2, Identidad e Información'!B8) | B23: MA | C23: MA | D23: ME | E23: MA | F23: ME | G23: ME | H23: MO | I23: ME | J23: ME | K23: ME | L23: MO | M23: MO | N23: MO | O23: MO | P23: ME | Q23: ME
A24: =CONCATENATE('2, Identidad e Información'!A9,": ",'2, Identidad e Información'!B9) | B24: ME | C24: ME | D24: ME | E24: ME | F24: MA | G24: ME | H24: MO | I24: MA | J24: MA | K24: MO | L24: ME | M24: ME | N24: ME | O24: MO | P24: ME | Q24: ME
A26: TABLA 6.23. RELEVANCIA DEL INCUMPLIMIENTO DE LOS CRITERIOS DE "ESTRUCTURA Y NAVEGACIÓN"
B27: Tipo de Sitio
A28: Criterio | B28: =B$3 | C28: =C$3 | D28: =D$3 | E28: =E$3 | F28: =F$3 | G28: =G$3 | H28: =H$3 | I28: =I$3 | ... Q28: =Q$3
A29: =CONCATENATE('3, Estructura y navegación'!A3,": ",'3, Estructura y navegación'!B3) | B29: MO | C29: MO | D29: MO | E29: MO | F29: MO | G29: MO | H29: MO | I29: MO | J29: MO | K29: MO | L29: MO | M29: MO | N29: MO | O29: MO | P29: MO | Q29: MO
A30: =CONCATENATE('3, Estructura y navegación'!A4,": ",'3, Estructura y navegación'!B4) | B30: MA | C30: ME | D30: MA | E30: MA | F30: ME | G30: MA | H30: ME | I30: MA | J30: ME | K30: ME | L30: MO | M30: ME | N30: MA | O30: ME | P30: MA | Q30: MA
A31: =CONCATENATE('3, Estructura y navegación'!A5,": ",'3, Estructura y navegación'!B5) | B31: MA | C31: MO | D31: MA | E31: MA | F31: ME | G31: ME | H31: MO | I31: ME | J31: ME | K31: ME | L31: ME | M31: MO | N31: ME | O31: MA | P31: MA | Q31: ME
A32: =CONCATENATE('3, Estructura y navegación'!A6,": ",'3, Estructura y navegación'!B6) | B32: MA | C32: MO | D32: MA | E32: MA | F32: ME | G32: ME | H32: ME | I32: MA | J32: MA | K32: ME | L32: ME | M32: ME | N32: MA | O32: ME | P32: ME | Q32: ME
A33: =CONCATENATE('3, Estructura y navegación'!A7,": ",'3, Estructura y navegación'!B7) | B33: MA | C33: MO | D33: MA | E33: MA | F33: ME | G33: ME | H33: ME | I33: MA | J33: ME | K33: ME | L33: MO | M33: MO | N33: MA | O33: MO | P33: ME | Q33: ME
A34: =CONCATENATE('3, Estructura y navegación'!A8,": ",'3, Estructura y navegación'!B8) | B34: MA | C34: MA | D34: MA | E34: MA | F34: MA | G34: MA | H34: MA | I34: MA | J34: MA | K34: ME | L34: ME | M34: ME | N34: MA | O34: MA | P34: MA | Q34: MA
A35: =CONCATENATE('3, Estructura y navegación'!A9,": ",'3, Estructura y navegación'!B9) | B35: MA | C35: ME | D35: MA | E35: MA | F35: MA | G35: ME | H35: ME | I35: MA | J35: ME | K35: ME | L35: ME | M35: ME | N35: MA | O35: MA | P35: MA | Q35: ME
A36: =CONCATENATE('3, Estructura y navegación'!A10,": ",'3, Estructura y navegación'!B10) | B36: MA | C36: ME | D36: MA | E36: MA | F36: ME | G36: MA | H36: ME | I36: MA | J36: ME | K36: ME | L36: MO | M36: ME | N36: MA | O36: MO | P36: ME | Q36: ME
A37: =CONCATENATE('3, Estructura y navegación'!A11,": ",'3, Estructura y navegación'!B11) | B37: CR | C37: ME | D37: MA | E37: CR | F37: ME | G37: MA | H37: MA | I37: MA | J37: MA | K37: ME | L37: ME | M37: ME | N37: MA | O37: MO | P37: MA | Q37: MA
A38: =CONCATENATE('3, Estructura y navegación'!A12,": ",'3, Estructura y navegación'!B12) | B38: MO | C38: ME | D38: MO | E38: ME | F38: MO | G38: MO | H38: ME | I38: MO | J38: MO | K38: MO | L38: MO | M38: MO | N38: MO | O38: ME | P38: MO | Q38: ME
A39: =CONCATENATE('3, Estructura y navegación'!A13,": ",'3, Estructura y navegación'!B13) | B39: ME | C39: MA | D39: ME | E39: MA | F39: ME | G39: ME | H39: MA | I39: ME | J39: ME | K39: ME | L39: MA | M39: ME | N39: MA | O39: MA | P39: ME | Q39: MA
A40: =CONCATENATE('3, Estructura y navegación'!A14,": ",'3, Estructura y navegación'!B14) | B40: ME | C40: ME | D40: ME | E40: ME | F40: ME | G40: ME | H40: MO | I40: ME | J40: ME | K40: ME | L40: ME | M40: ME | N40: ME | O40: MA | P40: ME | Q40: ME
... A42: =CONCATENATE('3, Estructura y navegación'!A16,": ",'3, Estructura y navegación'!B16) | B42: MA | C42: ME | D42: MA | E42: ME | F42: ME | G42: MO | H42: MO | I42: ME | J42: ME | K42: MO | L42: MO | M42: MO | N42: ME | O42: ME | P42: ME | Q42: ME
A44: TABLA 6.24. RELEVANCIA DEL INCUMPLIMIENTO DE LOS CRITERIOS DE "ROTULADO"
B45: Tipo de Sitio
A46: Criterio | B46: =B$3 | C46: =C$3 | D46: =D$3 | E46: =E$3 | F46: =F$3 | G46: =G$3 | H46: =H$3 | I46: =I$3 | ... Q46: =Q$3
A47: =CONCATENATE('4, Rotulado'!A3,": ",'4, Rotulado'!B3) | B47: MA | C47: ME | D47: MA | E47: MA | F47: ME | G47: ME | H47: ME | I47: ME | J47: ME | K47: ME | L47: MO | M47: ME | N47: ME | O47: MA | P47: ME | Q47: ME
A48: =CONCATENATE('4, Rotulado'!A4,": ",'4, Rotulado'!B4) | B48: ME | C48: MO | D48: MA | E48: MA | F48: ME | G48: ME | H48: ME | I48: ME | J48: ME | K48: MO | L48: MO | M48: MO | N48: MA | O48: ME | P48: MA | Q48: ME
A49: =CONCATENATE('4, Rotulado'!A5,": ",'4, Rotulado'!B5) | B49: MA | C49: ME | D49: MA | E49: MA | F49: ME | G49: ME | H49: ME | I49: ME | J49: ME | K49: MO | L49: MO | M49: ME | N49: MA | O49: MO | P49: ME | Q49: MO
A50: =CONCATENATE('4, Rotulado'!A6,": ",'4, Rotulado'!B6) | B50: ME | C50: ME | D50: ME | E50: ME | F50: MO | G50: ME | H50: MO | I50: MO | J50: MO | K50: MO | L50: MO | M50: ME | N50: ME | O50: ME | P50: ME | Q50: ME
A51: =CONCATENATE('4, Rotulado'!A7,": ",'4, Rotulado'!B7) | B51: ME | C51: MO | D51: ME | E51: ME | F51: ME | G51: ME | H51: ME | I51: ME | J51: ME | K51: ME | L51: ME | M51: ME | N51: ME | O51: ME | P51: ME | Q51: ME
A52: =CONCATENATE('4, Rotulado'!A8,": ",'4, Rotulado'!B8) | B52: ME | C52: MO | D52: MA | E52: MA | F52: MO | G52: ME | H52: MO | I52: ME | J52: ME | K52: ME | L52: ME | M52: MO | N52: ME | O52: ME | P52: MO | Q52: ME
A54: TABLA 6.25. RELEVANCIA DEL INCUMPLIMIENTO DE LOS CRITERIOS DE "LAYOUT"
B55: Tipo de Sitio
A56: Criterio | B56: =B$3 | C56: =C$3 | D56: =D$3 | E56: =E$3 | F56: =F$3 | G56: =G$3 | H56: =H$3 | I56: =I$3 | ... Q56: =Q$3
A57: =CONCATENATE('5, Layout de la página'!A3,": ",'5, Layout de la página'!B3) | B57: MA | C57: MO | D57: MA | E57: MA | F57: MA | G57: ME | H57: MO | I57: ME | J57: ME | K57: MO | L57: MO | M57: ME | N57: ME | O57: MO | P57: ME | Q57: ME
A58: =CONCATENATE('5, Layout de la página'!A4,": ",'5, Layout de la página'!B4) | B58: ME | C58: ME | D58: ME | E58: ME | F58: ME | G58: ME | H58: MO | I58: ME | J58: ME | K58: MO | L58: MO | M58: ME | N58: ME | O58: MA | P58: ME | Q58: ME
A59: =CONCATENATE('5, Layout de la página'!A5,": ",'5, Layout de la página'!B5) | B59: MA | C59: ME | D59: MA | E59: MA | F59: MA | G59: MA | H59: MO | I59: ME | J59: ME | K59: ME | L59: MO | M59: ME | N59: MA | O59: MA | P59: ME | Q59: ME
A60: =CONCATENATE('5, Layout de la página'!A6,": ",'5, Layout de la página'!B6) | B60: MA | C60: ME | D60: ME | E60: ME | F60: MA | G60: ME | H60: MO | I60: ME | J60: ME | K60: ME | L60: MO | M60: ME | N60: ME | O60: ME | P60: ME | Q60: ME
A61: =CONCATENATE('5, Layout de la página'!A7,": ",'5, Layout de la página'!B7) | B61: ME | C61: ME | D61: MA | E61: MA | F61: MA | G61: MA | H61: MO | I61: ME | J61: ME | K61: ME | L61: ME | M61: ME | N61: MA | O61: ME | P61: MA | Q61: ME
A62: =CONCATENATE('5, Layout de la página'!A8,": ",'5, Layout de la página'!B8) | B62: MA | C62: ME | D62: MA | E62: MA | F62: MA | G62: ME | H62: MO | I62: ME | J62: MA | K62: MA | L62: MO | M62: ME | N62: MA | O62: ME | P62: ME | Q62: ME
A63: =CONCATENATE('5, Layout de la página'!A9,": ",'5, Layout de la página'!B9) | B63: ME | C63: MO | D63: ME | E63: ME | F63: ME | G63: ME | H63: MO | I63: ME | J63: ME | K63: MO | L63: MO | M63: ME | N63: ME | O63: ME | P63: ME | Q63: MO
A64: =CONCATENATE('5, Layout de la página'!A10,": ",'5, Layout de la página'!B10) | B64: MA | C64: ME | D64: MA | E64: MA | F64: ME | G64: ME | H64: MO | I64: MA | J64: ME | K64: MO | L64: MO | M64: ME | N64: MO | O64: MA | P64: MO | Q64: MA
A65: =CONCATENATE('5, Layout de la página'!A11,": ",'5, Layout de la página'!B11) | B65: CR | C65: ME | D65: MA | E65: CR | F65: CR | G65: MA | H65: ME | I65: MA | J65: MA | K65: MA | L65: ME | M65: MA | N65: MA | O65: MA | P65: MA | Q65: MA
A66: =CONCATENATE('5, Layout de la página'!A12,": ",'5, Layout de la página'!B12) | B66: MA | C66: MA | D66: MO | E66: ME | F66: MA | G66: MO | H66: ME | I66: ME | J66: ME | K66: MO | L66: MO | M66: MO | N66: MO | O66: ME | P66: ME | Q66: ME
A68: TABLA 6.26. RELEVANCIA DEL INCUMPLIMIENTO DE LOS CRITERIOS DE "ENTENDIBILIDAD Y FACILIDAD EN LA INTERACCIÓN”
B69: Tipo de Sitio
A70: Criterio | B70: =B$3 | C70: =C$3 | D70: =D$3 | E70: =E$3 | F70: =F$3 | G70: =G$3 | H70: =H$3 | I70: =I$3 | ... Q70: =Q$3
A71: =CONCATENATE('6, Entendibilidad y Facilidad'!A3,": ",'6, Entendibilidad y Facilidad'!B3) | B71: CR | C71: CR | D71: MA | E71: MA | F71: MA | G71: ME | H71: MO | I71: MA | J71: MA | K71: MO | L71: MO | M71: ME | N71: ME | O71: MA | P71: ME | Q71: ME
A72: =CONCATENATE('6, Entendibilidad y Facilidad'!A4,": ",'6, Entendibilidad y Facilidad'!B4) | B72: ME | C72: ME | D72: ME | E72: ME | F72: ME | G72: ME | H72: MO | I72: ME | J72: ME | K72: ME | L72: ME | M72: ME | N72: ME | O72: MO | P72: ME | Q72: MO
A73: =CONCATENATE('6, Entendibilidad y Facilidad'!A5,": ",'6, Entendibilidad y Facilidad'!B5) | B73: ME | C73: MO | D73: MA | E73: ME | F73: MA | G73: ME | H73: MO | I73: ME | J73: MA | K73: ME | L73: MO | M73: ME | N73: ME | O73: MO | P73: ME | Q73: MO
A74: =CONCATENATE('6, Entendibilidad y Facilidad'!A6,": ",'6, Entendibilidad y Facilidad'!B6) | B74: MA | C74: MA | D74: ME | E74: MA | F74: ME | G74: ME | H74: MO | I74: ME | J74: ME | K74: ME | L74: MO | M74: ME | N74: ME | O74: MA | P74: MA | Q74: MA
A75: =CONCATENATE('6, Entendibilidad y Facilidad'!A7,": ",'6, Entendibilidad y Facilidad'!B7) | B75: MA | C75: MA | D75: MA | E75: MA | F75: ME | G75: ME | H75: MO | I75: ME | J75: ME | K75: ME | L75: ME | M75: ME | N75: MA | O75: MA | P75: MA | Q75: MA
A76: =CONCATENATE('6, Entendibilidad y Facilidad'!A8,": ",'6, Entendibilidad y Facilidad'!B8) | B76: MA | C76: ME | D76: MA | E76: MA | F76: MA | G76: ME | H76: ME | I76: ME | J76: ME | K76: MO | L76: MO | M76: MO | N76: MA | O76: MO | P76: MA | Q76: ME
A77: =CONCATENATE('6, Entendibilidad y Facilidad'!A9,": ",'6, Entendibilidad y Facilidad'!B9) | B77: MA | C77: ME | D77: MA | E77: MA | F77: ME | G77: ME | H77: MO | I77: ME | J77: ME | K77: MO | L77: ME | M77: ME | N77: ME | O77: ME | P77: MA | Q77: MA
A79: TABLA 6.27. RELEVANCIA DEL INCUMPLIMIENTO DE LOS CRITERIOS DE "CONTROL Y RETROALIMENTACIÓN"
B80: Tipo de Sitio
A81: Criterio | B81: =B$3 | C81: =C$3 | D81: =D$3 | E81: =E$3 | F81: =F$3 | G81: =G$3 | H81: =H$3 | I81: =I$3 | ... Q81: =Q$3
A82: =CONCATENATE('7, Control y Retoalimentación'!A3,": ",'7, Control y Retoalimentación'!B3) | B82: ME | C82: MO | D82: MA | E82: MA | F82: MO | G82: MO | H82: MO | I82: ME | J82: ME | K82: ME | L82: ME | M82: ME | N82: ME | O82: MA | P82: MA | Q82: MA
A83: =CONCATENATE('7, Control y Retoalimentación'!A4,": ",'7, Control y Retoalimentación'!B4) | B83: ME | C83: MO | D83: MA | E83: MA | F83: ME | G83: MO | H83: MO | I83: MO | J83: MO | K83: ME | L83: MO | M83: MO | N83: ME | O83: MA | P83: MA | Q83: ME
A84: =CONCATENATE('7, Control y Retoalimentación'!A5,": ",'7, Control y Retoalimentación'!B5) | B84: MA | C84: ME | D84: MA | E84: CR | F84: ME | G84: MO | H84: ME | I84: ME | J84: ME | K84: MO | L84: MO | M84: MO | N84: ME | O84: MA | P84: ME | Q84: ME
A85: =CONCATENATE('7, Control y Retoalimentación'!A6,": ",'7, Control y Retoalimentación'!B6) | B85: CR | C85: ME | D85: MA | E85: CR | F85: MO | G85: MA | H85: ME | I85: ME | J85: ME | K85: MO | L85: MO | M85: ME | N85: MA | O85: ME | P85: MA | Q85: MA
A86: =CONCATENATE('7, Control y Retoalimentación'!A7,": ",'7, Control y Retoalimentación'!B7) | B86: MA | C86: MO | D86: MO | E86: MA | F86: MO | G86: MA | H86: MO | I86: MO | J86: ME | K86: MO | L86: MO | M86: ME | N86: ME | O86: ME | P86: ME | Q86: MA
A87: =CONCATENATE('7, Control y Retoalimentación'!A8,": ",'7, Control y Retoalimentación'!B8) | B87: MA | C87: CR | D87: MO | E87: CR | F87: ME | G87: MA | H87: CR | I87: MO | J87: ME | K87: MA | L87: MA | M87: MO | N87: MA | O87: CR | P87: CR | Q87: MA
A88: =CONCATENATE('7, Control y Retoalimentación'!A9,": ",'7, Control y Retoalimentación'!B9) | B88: MA | C88: ME | D88: MA | E88: CR | F88: ME | G88: MO | H88: ME | I88: ME | J88: MA | K88: ME | L88: ME | M88: ME | N88: ME | O88: MA | P88: MA | Q88: MA
A89: =CONCATENATE('7, Control y Retoalimentación'!A10,": ",'7, Control y Retoalimentación'!B10) | B89: MA | C89: ME | D89: MA | E89: MA | F89: ME | G89: ME | H89: MO | I89: ME | J89: MA | K89: ME | L89: ME | M89: MO | N89: ME | O89: MA | P89: ME | Q89: MA
A90: =CONCATENATE('7, Control y Retoalimentación'!A11,": ",'7, Control y Retoalimentación'!B11) | B90: MA | C90: MO | D90: ME | E90: CR | F90: ME | G90: ME | H90: MO | I90: ME | J90: ME | K90: MO | L90: MO | M90: ME | N90: ME | O90: MA | P90: MO | Q90: ME
A91: =CONCATENATE('7, Control y Retoalimentación'!A12,": ",'7, Control y Retoalimentación'!B12) | B91: MA | C91: ME | D91: MO | E91: MA | F91: MO | G91: ME | H91: MO | I91: MO | J91: ME | K91: MO | L91: MO | M91: MO | N91: ME | O91: MO | P91: ME | Q91: ME
A93: TABLA 6.28. RELEVANCIA DEL INCUMPLIMIENTO DE LOS CRITERIOS DE "ELEMENTOS MULTIMEDIA"
B94: Tipo de Sitio
A95: Criterio | B95: =B$3 | C95: =C$3 | D95: =D$3 | E95: =E$3 | F95: =F$3 | G95: =G$3 | H95: =H$3 | I95: =I$3 | ... Q95: =Q$3
A96: =CONCATENATE('8, Elementos multimedia'!A3,": ",'8, Elementos multimedia'!B3) | B96: ME | C96: MO | D96: MO | E96: MO | F96: MA | G96: MA | H96: MO | I96: ME | J96: MO | K96: MO | L96: MA | M96: MO | N96: MA | O96: MA | P96: ME | Q96: MO
A97: =CONCATENATE('8, Elementos multimedia'!A4,": ",'8, Elementos multimedia'!B4) | B97: ME | C97: MO | D97: MO | E97: CR | F97: MA | G97: ME | H97: MA | I97: MA | J97: MA | K97: MO | L97: MA | M97: MO | N97: MA | O97: CR | P97: MA | Q97: ME
A98: =CONCATENATE('8, Elementos multimedia'!A5,": ",'8, Elementos multimedia'!B5) | B98: MO | C98: MO | D98: MA | E98: MA | F98: MA | G98: ME | H98: MO | I98: ME | J98: ME | K98: MO | L98: MA | M98: MO | N98: MA | O98: MA | P98: MA | Q98: ME
A99: =CONCATENATE('8, Elementos multimedia'!A6,": ",'8, Elementos multimedia'!B6) | B99: ME | C99: ME | D99: MO | E99: ME | F99: ME | G99: ME | H99: ME | I99: ME | J99: ME | K99: MO | L99: ME | M99: ME | N99: ME | O99: MA | P99: ME | Q99: ME
A100: =CONCATENATE('8, Elementos multimedia'!A7,": ",'8, Elementos multimedia'!B7) | B100: MA | C100: MO | D100: MA | E100: MA | F100: ME | G100: MA | H100: ME | I100: ME | J100: MA | K100: MO | L100: MO | M100: ME | N100: ME | O100: MA | P100: MA | Q100: MA
A101: =CONCATENATE('8, Elementos multimedia'!A8,": ",'8, Elementos multimedia'!B8) | B101: MO | C101: MO | D101: MO | E101: MO | F101: MA | G101: MO | H101: MO | I101: MO | J101: MO | K101: MO | L101: MO | M101: MO | N101: MO | O101: MO | P101: MO | Q101: MO
A103: TABLA 6.29. RELEVANCIA DEL INCUMPLIMIENTO DE LOS CRITERIOS DE "BÚSQUEDA"
B104: Tipo de Sitio
A105: Criterio | B105: =B$3 | C105: =C$3 | D105: =D$3 | E105: =E$3 | F105: =F$3 | G105: =G$3 | H105: =H$3 | I105: =I$3 | ... Q105: =Q$3
A106: =CONCATENATE('9, Búsqueda'!A3,": ",'9, Búsqueda'!B3) | B106: CR | C106: MA | D106: MO | E106: CR | F106: MA | G106: MO | H106: ME | I106: MA | J106: MA | K106: MO | L106: ME | M106: MO | N106: MO | O106: MA | P106: MA | Q106: MA
A107: =CONCATENATE('9, Búsqueda'!A4,": ",'9, Búsqueda'!B4) | B107: MA | C107: MO | D107: MA | E107: MA | F107: ME | G107: MA | H107: ME | I107: ME | J107: ME | K107: ME | L107: ME | M107: ME | N107: MA | O107: MA | P107: MA | Q107: MA
A108: =CONCATENATE('9, Búsqueda'!A5,": ",'9, Búsqueda'!B5) | B108: MA | C108: ME | D108: MA | E108: MA | F108: MA | G108: ME | H108: MA | I108: ME | J108: ME | K108: MO | L108: ME | M108: MO | N108: MA | O108: ME | P108: ME | Q108: ME
A109: =CONCATENATE('9, Búsqueda'!A6,": ",'9, Búsqueda'!B6) | B109: MA | C109: MO | D109: ME | E109: MA | F109: ME | G109: ME | H109: ME | I109: MA | J109: ME | K109: MA | L109: MO | M109: MO | N109: MA | O109: MA | P109: MA | Q109: MA
...

Sheet Valores
A3: Datos internos | C3: No modificar, son los datos de las combos
A5: 0 | C5: NTS | E5: Administración Pública / Institucional | J5: CR | K5: 8 | M5: NTS | N5: 0
A6: 1 | C6: NEP | E6: Banca electrónica | J6: MA | K6: 4 | M6: NEP | N6: 2.5
A7: 2 | C7: NPP | E7: Blog | J7: ME | K7: 2 | M7: NPP | N7: 5
A8: 3 | C8: NPI | E8: Comercio electrónico | J8: MO | K8: 1 | M8: NPI | N8: 7.5
A9: 4 | C9: S | E9: Comunicación / Noticias | M9: S | N9: 10
A10: 5 | C10: NA | E10: Corporativo / Empresas | M10: 0 | N10: 0
A11: 6 | E11: Descargas | M11: 1 | N11: 1
A12: 7 | E12: Educativo / Formativo | M12: 2 | N12: 2
A13: 8 | E13: Entornos colaborativos / Wikis | M13: 3 | N13: 3
A14: 9 | E14: Foros / Chat | M14: 4 | N14: 4
A15: 10 | E15: Ocio / Entretenimiento | M15: 5 | N15: 5
A16: NA | E16: Personal | M16: 6 | N16: 6
E17: Portal de Servicios | M17: 7 | N17: 7
E18: Servicios interactivos basados en imágenes | M18: 8 | N18: 8
E19: Servicios interactivos no basados en imágenes | M19: 9 | N19: 9
E20: Webmail / Correo | M20: 10 | N20: 10
M21: NA | N21: 0
